{"@t":"2025-08-29T05:44:44.2407330Z","@mt":"Deleted {count} ContentVersion(s).","count":10,"SourceContext":"Umbraco.Web.Scheduling.ContentVersionCleanup","ProcessId":120252,"ProcessName":"w3wp","ThreadId":184,"AppDomainId":2,"AppDomainAppId":"LMW3SVC14ROOT","MachineName":"DESKTOP-3G1QN35","Log4NetLevel":"INFO "}
{"@t":"2025-08-29T11:02:40.9712815Z","@mt":"Failed (will repeat).","@l":"Error","@x":"System.Data.SqlClient.SqlException (0x80131904): Execution Timeout Expired.  The timeout period elapsed prior to completion of the operation or the server is not responding. ---> System.ComponentModel.Win32Exception (0x80004005): The wait operation timed out\r\n   at System.Data.SqlClient.SqlInternalConnection.OnError(SqlException exception, Boolean breakConnection, Action`1 wrapCloseInAction)\r\n   at System.Data.SqlClient.TdsParser.ThrowExceptionAndWarning(TdsParserStateObject stateObj, Boolean callerHasConnectionLock, Boolean asyncClose)\r\n   at System.Data.SqlClient.TdsParserStateObject.ReadSniError(TdsParserStateObject stateObj, UInt32 error)\r\n   at System.Data.SqlClient.TdsParserStateObject.ReadSniSyncOverAsync()\r\n   at System.Data.SqlClient.TdsParserStateObject.TryReadNetworkPacket()\r\n   at System.Data.SqlClient.TdsParserStateObject.TryPrepareBuffer()\r\n   at System.Data.SqlClient.TdsParserStateObject.TryReadByte(Byte& value)\r\n   at System.Data.SqlClient.TdsParser.TryRun(RunBehavior runBehavior, SqlCommand cmdHandler, SqlDataReader dataStream, BulkCopySimpleResultSet bulkCopyHandler, TdsParserStateObject stateObj, Boolean& dataReady)\r\n   at System.Data.SqlClient.TdsParser.Run(RunBehavior runBehavior, SqlCommand cmdHandler, SqlDataReader dataStream, BulkCopySimpleResultSet bulkCopyHandler, TdsParserStateObject stateObj)\r\n   at System.Data.SqlClient.TdsParser.TdsExecuteTransactionManagerRequest(Byte[] buffer, TransactionManagerRequestType request, String transactionName, TransactionManagerIsolationLevel isoLevel, Int32 timeout, SqlInternalTransaction transaction, TdsParserStateObject stateObj, Boolean isDelegateControlRequest)\r\n   at System.Data.SqlClient.SqlInternalConnectionTds.ExecuteTransactionYukon(TransactionRequest transactionRequest, String transactionName, IsolationLevel iso, SqlInternalTransaction internalTransaction, Boolean isDelegateControlRequest)\r\n   at System.Data.SqlClient.SqlInternalConnection.BeginSqlTransaction(IsolationLevel iso, String transactionName, Boolean shouldReconnect)\r\n   at System.Data.SqlClient.SqlConnection.BeginTransaction(IsolationLevel iso, String transactionName)\r\n   at System.Data.SqlClient.SqlConnection.BeginDbTransaction(IsolationLevel isolationLevel)\r\n   at StackExchange.Profiling.Data.ProfiledDbConnection.BeginDbTransaction(IsolationLevel isolationLevel) in C:\\projects\\dotnet\\src\\MiniProfiler.Shared\\Data\\ProfiledDbConnection.cs:line 138\r\n   at NPoco.Database.BeginTransaction(IsolationLevel isolationLevel)\r\n   at Umbraco.Core.Scoping.Scope.get_Database() in D:\\a\\1\\s\\src\\Umbraco.Core\\Scoping\\Scope.cs:line 330\r\n   at Umbraco.Core.Sync.DatabaseServerMessenger.Sync() in D:\\a\\1\\s\\src\\Umbraco.Core\\Sync\\DatabaseServerMessenger.cs:line 263\r\n   at Umbraco.Web.Compose.DatabaseServerRegistrarAndMessengerComponent.InstructionProcessTask.PerformRun() in D:\\a\\1\\s\\src\\Umbraco.Web\\Compose\\DatabaseServerRegistrarAndMessengerComponent.cs:line 163\r\nClientConnectionId:945874aa-4861-4264-b706-7b846fde778a\r\nError Number:-2,State:0,Class:11","SourceContext":"Umbraco.Web.Compose.DatabaseServerRegistrarAndMessengerComponent+InstructionProcessTask","ProcessId":120252,"ProcessName":"w3wp","ThreadId":311,"AppDomainId":2,"AppDomainAppId":"LMW3SVC14ROOT","MachineName":"DESKTOP-3G1QN35","Log4NetLevel":"ERROR"}
{"@t":"2025-08-29T14:44:48.6211626Z","@mt":"An unhandled exception occurred","@l":"Error","@x":"System.NullReferenceException: Object reference not set to an instance of an object.\r\n   at TSPadel_Umbraco.Extensions.MediaHelper.GetUserPlatform(HttpRequest request) in C:\\Development\\TSPadel\\TSPadel_Umbraco\\Extensions\\MediaHelper.cs:line 152\r\n   at TSPadel_Umbraco.Extensions.MediaHelper.GetUserEnvironment(HttpRequest request) in C:\\Development\\TSPadel\\TSPadel_Umbraco\\Extensions\\MediaHelper.cs:line 144\r\n   at TSPadel_Umbraco.Extensions.MediaHelper.GetMediaURL(IPublishedContent contentItem, String propertyName, Int32 ImageWidth, HttpRequest request) in C:\\Development\\TSPadel\\TSPadel_Umbraco\\Extensions\\MediaHelper.cs:line 59\r\n   at ASP._Page_Views_Partials_Header_cshtml.Execute() in C:\\Development\\TSPadel\\TSPadel_Umbraco\\Views\\Partials\\Header.cshtml:line 59\r\n   at System.Web.WebPages.WebPageBase.ExecutePageHierarchy()\r\n   at System.Web.Mvc.WebViewPage.ExecutePageHierarchy()\r\n   at System.Web.WebPages.WebPageBase.ExecutePageHierarchy(WebPageContext pageContext, TextWriter writer, WebPageRenderingBase startPage)\r\n   at Umbraco.Web.Mvc.ProfilingView.Render(ViewContext viewContext, TextWriter writer) in D:\\a\\1\\s\\src\\Umbraco.Web\\Mvc\\ProfilingView.cs:line 25\r\n   at System.Web.Mvc.Html.PartialExtensions.Partial(HtmlHelper htmlHelper, String partialViewName, Object model, ViewDataDictionary viewData)\r\n   at ASP._Page_Views_Master_cshtml.Execute() in C:\\Development\\TSPadel\\TSPadel_Umbraco\\Views\\Master.cshtml:line 52\r\n   at System.Web.WebPages.WebPageBase.ExecutePageHierarchy()\r\n   at System.Web.Mvc.WebViewPage.ExecutePageHierarchy()\r\n   at System.Web.WebPages.WebPageBase.ExecutePageHierarchy(WebPageContext pageContext, TextWriter writer, WebPageRenderingBase startPage)\r\n   at System.Web.WebPages.WebPageBase.<>c__DisplayClass40_0.<RenderPageCore>b__0(TextWriter writer)\r\n   at System.Web.WebPages.WebPageBase.Write(HelperResult result)\r\n   at System.Web.WebPages.WebPageBase.RenderSurrounding(String partialViewName, Action`1 body)\r\n   at System.Web.WebPages.WebPageBase.PopContext()\r\n   at Umbraco.Web.Mvc.ProfilingView.Render(ViewContext viewContext, TextWriter writer) in D:\\a\\1\\s\\src\\Umbraco.Web\\Mvc\\ProfilingView.cs:line 25\r\n   at System.Web.Mvc.ViewResultBase.ExecuteResult(ControllerContext context)\r\n   at System.Web.Mvc.ControllerActionInvoker.InvokeActionResultFilterRecursive(IList`1 filters, Int32 filterIndex, ResultExecutingContext preContext, ControllerContext controllerContext, ActionResult actionResult)\r\n   at System.Web.Mvc.ControllerActionInvoker.InvokeActionResultFilterRecursive(IList`1 filters, Int32 filterIndex, ResultExecutingContext preContext, ControllerContext controllerContext, ActionResult actionResult)\r\n   at System.Web.Mvc.ControllerActionInvoker.InvokeActionResultFilterRecursive(IList`1 filters, Int32 filterIndex, ResultExecutingContext preContext, ControllerContext controllerContext, ActionResult actionResult)\r\n   at System.Web.Mvc.ControllerActionInvoker.InvokeActionResultFilterRecursive(IList`1 filters, Int32 filterIndex, ResultExecutingContext preContext, ControllerContext controllerContext, ActionResult actionResult)\r\n   at System.Web.Mvc.ControllerActionInvoker.InvokeActionResultWithFilters(ControllerContext controllerContext, IList`1 filters, ActionResult actionResult)\r\n   at System.Web.Mvc.Async.AsyncControllerActionInvoker.<>c__DisplayClass3_1.<BeginInvokeAction>b__1(IAsyncResult asyncResult)\r\n   at System.Web.Mvc.Async.AsyncControllerActionInvoker.EndInvokeAction(IAsyncResult asyncResult)\r\n   at System.Web.Mvc.Controller.<>c.<BeginExecuteCore>b__152_1(IAsyncResult asyncResult, ExecuteCoreState innerState)\r\n   at System.Web.Mvc.Async.AsyncResultWrapper.WrappedAsyncVoid`1.CallEndDelegate(IAsyncResult asyncResult)\r\n   at System.Web.Mvc.Controller.EndExecuteCore(IAsyncResult asyncResult)\r\n   at System.Web.Mvc.Async.AsyncResultWrapper.WrappedAsyncVoid`1.CallEndDelegate(IAsyncResult asyncResult)\r\n   at System.Web.Mvc.Controller.EndExecute(IAsyncResult asyncResult)\r\n   at System.Web.Mvc.MvcHandler.<>c.<BeginProcessRequest>b__20_1(IAsyncResult asyncResult, ProcessRequestState innerState)\r\n   at System.Web.Mvc.Async.AsyncResultWrapper.WrappedAsyncVoid`1.CallEndDelegate(IAsyncResult asyncResult)\r\n   at System.Web.Mvc.MvcHandler.EndProcessRequest(IAsyncResult asyncResult)\r\n   at System.Web.HttpApplication.CallHandlerExecutionStep.System.Web.HttpApplication.IExecutionStep.Execute()\r\n   at System.Web.HttpApplication.ExecuteStepImpl(IExecutionStep step)\r\n   at System.Web.HttpApplication.ExecuteStep(IExecutionStep step, Boolean& completedSynchronously)","SourceContext":"Umbraco.Web.UmbracoApplicationBase","ProcessId":120252,"ProcessName":"w3wp","ThreadId":556,"AppDomainId":2,"AppDomainAppId":"LMW3SVC14ROOT","MachineName":"DESKTOP-3G1QN35","Log4NetLevel":"ERROR","HttpSessionId":"kdgs5i0ap0graa2xvwge2wsr","HttpRequestNumber":15,"HttpRequestId":"d626073d-1b8f-4e32-baf5-9fab7513dada"}
{"@t":"2025-08-29T14:44:48.6391628Z","@mt":"An unhandled exception occurred","@l":"Error","@x":"System.NullReferenceException: Object reference not set to an instance of an object.\r\n   at TSPadel_Umbraco.Extensions.MediaHelper.GetUserPlatform(HttpRequest request) in C:\\Development\\TSPadel\\TSPadel_Umbraco\\Extensions\\MediaHelper.cs:line 152\r\n   at TSPadel_Umbraco.Extensions.MediaHelper.GetUserEnvironment(HttpRequest request) in C:\\Development\\TSPadel\\TSPadel_Umbraco\\Extensions\\MediaHelper.cs:line 144\r\n   at TSPadel_Umbraco.Extensions.MediaHelper.GetMediaURL(IPublishedContent contentItem, String propertyName, Int32 ImageWidth, HttpRequest request) in C:\\Development\\TSPadel\\TSPadel_Umbraco\\Extensions\\MediaHelper.cs:line 59\r\n   at ASP._Page_Views_Partials_Header_cshtml.Execute() in C:\\Development\\TSPadel\\TSPadel_Umbraco\\Views\\Partials\\Header.cshtml:line 59\r\n   at System.Web.WebPages.WebPageBase.ExecutePageHierarchy()\r\n   at System.Web.Mvc.WebViewPage.ExecutePageHierarchy()\r\n   at System.Web.WebPages.WebPageBase.ExecutePageHierarchy(WebPageContext pageContext, TextWriter writer, WebPageRenderingBase startPage)\r\n   at Umbraco.Web.Mvc.ProfilingView.Render(ViewContext viewContext, TextWriter writer) in D:\\a\\1\\s\\src\\Umbraco.Web\\Mvc\\ProfilingView.cs:line 25\r\n   at System.Web.Mvc.Html.PartialExtensions.Partial(HtmlHelper htmlHelper, String partialViewName, Object model, ViewDataDictionary viewData)\r\n   at ASP._Page_Views_Master_cshtml.Execute() in C:\\Development\\TSPadel\\TSPadel_Umbraco\\Views\\Master.cshtml:line 52\r\n   at System.Web.WebPages.WebPageBase.ExecutePageHierarchy()\r\n   at System.Web.Mvc.WebViewPage.ExecutePageHierarchy()\r\n   at System.Web.WebPages.WebPageBase.ExecutePageHierarchy(WebPageContext pageContext, TextWriter writer, WebPageRenderingBase startPage)\r\n   at System.Web.WebPages.WebPageBase.<>c__DisplayClass40_0.<RenderPageCore>b__0(TextWriter writer)\r\n   at System.Web.WebPages.WebPageBase.Write(HelperResult result)\r\n   at System.Web.WebPages.WebPageBase.RenderSurrounding(String partialViewName, Action`1 body)\r\n   at System.Web.WebPages.WebPageBase.PopContext()\r\n   at Umbraco.Web.Mvc.ProfilingView.Render(ViewContext viewContext, TextWriter writer) in D:\\a\\1\\s\\src\\Umbraco.Web\\Mvc\\ProfilingView.cs:line 25\r\n   at System.Web.Mvc.ViewResultBase.ExecuteResult(ControllerContext context)\r\n   at System.Web.Mvc.ControllerActionInvoker.InvokeActionResultFilterRecursive(IList`1 filters, Int32 filterIndex, ResultExecutingContext preContext, ControllerContext controllerContext, ActionResult actionResult)\r\n   at System.Web.Mvc.ControllerActionInvoker.InvokeActionResultFilterRecursive(IList`1 filters, Int32 filterIndex, ResultExecutingContext preContext, ControllerContext controllerContext, ActionResult actionResult)\r\n   at System.Web.Mvc.ControllerActionInvoker.InvokeActionResultFilterRecursive(IList`1 filters, Int32 filterIndex, ResultExecutingContext preContext, ControllerContext controllerContext, ActionResult actionResult)\r\n   at System.Web.Mvc.ControllerActionInvoker.InvokeActionResultFilterRecursive(IList`1 filters, Int32 filterIndex, ResultExecutingContext preContext, ControllerContext controllerContext, ActionResult actionResult)\r\n   at System.Web.Mvc.ControllerActionInvoker.InvokeActionResultWithFilters(ControllerContext controllerContext, IList`1 filters, ActionResult actionResult)\r\n   at System.Web.Mvc.Async.AsyncControllerActionInvoker.<>c__DisplayClass3_1.<BeginInvokeAction>b__1(IAsyncResult asyncResult)\r\n   at System.Web.Mvc.Async.AsyncControllerActionInvoker.EndInvokeAction(IAsyncResult asyncResult)\r\n   at System.Web.Mvc.Controller.<>c.<BeginExecuteCore>b__152_1(IAsyncResult asyncResult, ExecuteCoreState innerState)\r\n   at System.Web.Mvc.Async.AsyncResultWrapper.WrappedAsyncVoid`1.CallEndDelegate(IAsyncResult asyncResult)\r\n   at System.Web.Mvc.Controller.EndExecuteCore(IAsyncResult asyncResult)\r\n   at System.Web.Mvc.Async.AsyncResultWrapper.WrappedAsyncVoid`1.CallEndDelegate(IAsyncResult asyncResult)\r\n   at System.Web.Mvc.Controller.EndExecute(IAsyncResult asyncResult)\r\n   at System.Web.Mvc.MvcHandler.<>c.<BeginProcessRequest>b__20_1(IAsyncResult asyncResult, ProcessRequestState innerState)\r\n   at System.Web.Mvc.Async.AsyncResultWrapper.WrappedAsyncVoid`1.CallEndDelegate(IAsyncResult asyncResult)\r\n   at System.Web.Mvc.MvcHandler.EndProcessRequest(IAsyncResult asyncResult)\r\n   at System.Web.HttpApplication.CallHandlerExecutionStep.System.Web.HttpApplication.IExecutionStep.Execute()\r\n   at System.Web.HttpApplication.ExecuteStepImpl(IExecutionStep step)\r\n   at System.Web.HttpApplication.ExecuteStep(IExecutionStep step, Boolean& completedSynchronously)","SourceContext":"Umbraco.Web.UmbracoApplicationBase","ProcessId":120252,"ProcessName":"w3wp","ThreadId":179,"AppDomainId":2,"AppDomainAppId":"LMW3SVC14ROOT","MachineName":"DESKTOP-3G1QN35","Log4NetLevel":"ERROR","HttpSessionId":"x04lb323ihvgwyyxguowgjbq","HttpRequestNumber":16,"HttpRequestId":"f7b33d15-fbb4-4ada-9fc4-a1c543db03ca"}
{"@t":"2025-08-29T14:44:48.6461641Z","@mt":"An unhandled exception occurred","@l":"Error","@x":"System.NullReferenceException: Object reference not set to an instance of an object.\r\n   at TSPadel_Umbraco.Extensions.MediaHelper.GetUserPlatform(HttpRequest request) in C:\\Development\\TSPadel\\TSPadel_Umbraco\\Extensions\\MediaHelper.cs:line 152\r\n   at TSPadel_Umbraco.Extensions.MediaHelper.GetUserEnvironment(HttpRequest request) in C:\\Development\\TSPadel\\TSPadel_Umbraco\\Extensions\\MediaHelper.cs:line 144\r\n   at TSPadel_Umbraco.Extensions.MediaHelper.GetMediaURL(IPublishedContent contentItem, String propertyName, Int32 ImageWidth, HttpRequest request) in C:\\Development\\TSPadel\\TSPadel_Umbraco\\Extensions\\MediaHelper.cs:line 59\r\n   at ASP._Page_Views_Partials_Header_cshtml.Execute() in C:\\Development\\TSPadel\\TSPadel_Umbraco\\Views\\Partials\\Header.cshtml:line 59\r\n   at System.Web.WebPages.WebPageBase.ExecutePageHierarchy()\r\n   at System.Web.Mvc.WebViewPage.ExecutePageHierarchy()\r\n   at System.Web.WebPages.WebPageBase.ExecutePageHierarchy(WebPageContext pageContext, TextWriter writer, WebPageRenderingBase startPage)\r\n   at Umbraco.Web.Mvc.ProfilingView.Render(ViewContext viewContext, TextWriter writer) in D:\\a\\1\\s\\src\\Umbraco.Web\\Mvc\\ProfilingView.cs:line 25\r\n   at System.Web.Mvc.Html.PartialExtensions.Partial(HtmlHelper htmlHelper, String partialViewName, Object model, ViewDataDictionary viewData)\r\n   at ASP._Page_Views_Master_cshtml.Execute() in C:\\Development\\TSPadel\\TSPadel_Umbraco\\Views\\Master.cshtml:line 52\r\n   at System.Web.WebPages.WebPageBase.ExecutePageHierarchy()\r\n   at System.Web.Mvc.WebViewPage.ExecutePageHierarchy()\r\n   at System.Web.WebPages.WebPageBase.ExecutePageHierarchy(WebPageContext pageContext, TextWriter writer, WebPageRenderingBase startPage)\r\n   at System.Web.WebPages.WebPageBase.<>c__DisplayClass40_0.<RenderPageCore>b__0(TextWriter writer)\r\n   at System.Web.WebPages.WebPageBase.Write(HelperResult result)\r\n   at System.Web.WebPages.WebPageBase.RenderSurrounding(String partialViewName, Action`1 body)\r\n   at System.Web.WebPages.WebPageBase.PopContext()\r\n   at Umbraco.Web.Mvc.ProfilingView.Render(ViewContext viewContext, TextWriter writer) in D:\\a\\1\\s\\src\\Umbraco.Web\\Mvc\\ProfilingView.cs:line 25\r\n   at System.Web.Mvc.ViewResultBase.ExecuteResult(ControllerContext context)\r\n   at System.Web.Mvc.ControllerActionInvoker.InvokeActionResultFilterRecursive(IList`1 filters, Int32 filterIndex, ResultExecutingContext preContext, ControllerContext controllerContext, ActionResult actionResult)\r\n   at System.Web.Mvc.ControllerActionInvoker.InvokeActionResultFilterRecursive(IList`1 filters, Int32 filterIndex, ResultExecutingContext preContext, ControllerContext controllerContext, ActionResult actionResult)\r\n   at System.Web.Mvc.ControllerActionInvoker.InvokeActionResultFilterRecursive(IList`1 filters, Int32 filterIndex, ResultExecutingContext preContext, ControllerContext controllerContext, ActionResult actionResult)\r\n   at System.Web.Mvc.ControllerActionInvoker.InvokeActionResultFilterRecursive(IList`1 filters, Int32 filterIndex, ResultExecutingContext preContext, ControllerContext controllerContext, ActionResult actionResult)\r\n   at System.Web.Mvc.ControllerActionInvoker.InvokeActionResultWithFilters(ControllerContext controllerContext, IList`1 filters, ActionResult actionResult)\r\n   at System.Web.Mvc.Async.AsyncControllerActionInvoker.<>c__DisplayClass3_1.<BeginInvokeAction>b__1(IAsyncResult asyncResult)\r\n   at System.Web.Mvc.Async.AsyncControllerActionInvoker.EndInvokeAction(IAsyncResult asyncResult)\r\n   at System.Web.Mvc.Controller.<>c.<BeginExecuteCore>b__152_1(IAsyncResult asyncResult, ExecuteCoreState innerState)\r\n   at System.Web.Mvc.Async.AsyncResultWrapper.WrappedAsyncVoid`1.CallEndDelegate(IAsyncResult asyncResult)\r\n   at System.Web.Mvc.Controller.EndExecuteCore(IAsyncResult asyncResult)\r\n   at System.Web.Mvc.Async.AsyncResultWrapper.WrappedAsyncVoid`1.CallEndDelegate(IAsyncResult asyncResult)\r\n   at System.Web.Mvc.Controller.EndExecute(IAsyncResult asyncResult)\r\n   at System.Web.Mvc.MvcHandler.<>c.<BeginProcessRequest>b__20_1(IAsyncResult asyncResult, ProcessRequestState innerState)\r\n   at System.Web.Mvc.Async.AsyncResultWrapper.WrappedAsyncVoid`1.CallEndDelegate(IAsyncResult asyncResult)\r\n   at System.Web.Mvc.MvcHandler.EndProcessRequest(IAsyncResult asyncResult)\r\n   at System.Web.HttpApplication.CallHandlerExecutionStep.System.Web.HttpApplication.IExecutionStep.Execute()\r\n   at System.Web.HttpApplication.ExecuteStepImpl(IExecutionStep step)\r\n   at System.Web.HttpApplication.ExecuteStep(IExecutionStep step, Boolean& completedSynchronously)","SourceContext":"Umbraco.Web.UmbracoApplicationBase","ProcessId":120252,"ProcessName":"w3wp","ThreadId":749,"AppDomainId":2,"AppDomainAppId":"LMW3SVC14ROOT","MachineName":"DESKTOP-3G1QN35","Log4NetLevel":"ERROR","HttpSessionId":"m1lukni2mvsoi5eb1mtjthpd","HttpRequestNumber":17,"HttpRequestId":"a3d3d7ce-7a78-4688-a260-6f0b4448920e"}
{"@t":"2025-08-29T14:44:48.6531625Z","@mt":"An unhandled exception occurred","@l":"Error","@x":"System.NullReferenceException: Object reference not set to an instance of an object.\r\n   at TSPadel_Umbraco.Extensions.MediaHelper.GetUserPlatform(HttpRequest request) in C:\\Development\\TSPadel\\TSPadel_Umbraco\\Extensions\\MediaHelper.cs:line 152\r\n   at TSPadel_Umbraco.Extensions.MediaHelper.GetUserEnvironment(HttpRequest request) in C:\\Development\\TSPadel\\TSPadel_Umbraco\\Extensions\\MediaHelper.cs:line 144\r\n   at TSPadel_Umbraco.Extensions.MediaHelper.GetMediaURL(IPublishedContent contentItem, String propertyName, Int32 ImageWidth, HttpRequest request) in C:\\Development\\TSPadel\\TSPadel_Umbraco\\Extensions\\MediaHelper.cs:line 59\r\n   at ASP._Page_Views_Partials_Header_cshtml.Execute() in C:\\Development\\TSPadel\\TSPadel_Umbraco\\Views\\Partials\\Header.cshtml:line 59\r\n   at System.Web.WebPages.WebPageBase.ExecutePageHierarchy()\r\n   at System.Web.Mvc.WebViewPage.ExecutePageHierarchy()\r\n   at System.Web.WebPages.WebPageBase.ExecutePageHierarchy(WebPageContext pageContext, TextWriter writer, WebPageRenderingBase startPage)\r\n   at Umbraco.Web.Mvc.ProfilingView.Render(ViewContext viewContext, TextWriter writer) in D:\\a\\1\\s\\src\\Umbraco.Web\\Mvc\\ProfilingView.cs:line 25\r\n   at System.Web.Mvc.Html.PartialExtensions.Partial(HtmlHelper htmlHelper, String partialViewName, Object model, ViewDataDictionary viewData)\r\n   at ASP._Page_Views_Master_cshtml.Execute() in C:\\Development\\TSPadel\\TSPadel_Umbraco\\Views\\Master.cshtml:line 52\r\n   at System.Web.WebPages.WebPageBase.ExecutePageHierarchy()\r\n   at System.Web.Mvc.WebViewPage.ExecutePageHierarchy()\r\n   at System.Web.WebPages.WebPageBase.ExecutePageHierarchy(WebPageContext pageContext, TextWriter writer, WebPageRenderingBase startPage)\r\n   at System.Web.WebPages.WebPageBase.<>c__DisplayClass40_0.<RenderPageCore>b__0(TextWriter writer)\r\n   at System.Web.WebPages.WebPageBase.Write(HelperResult result)\r\n   at System.Web.WebPages.WebPageBase.RenderSurrounding(String partialViewName, Action`1 body)\r\n   at System.Web.WebPages.WebPageBase.PopContext()\r\n   at Umbraco.Web.Mvc.ProfilingView.Render(ViewContext viewContext, TextWriter writer) in D:\\a\\1\\s\\src\\Umbraco.Web\\Mvc\\ProfilingView.cs:line 25\r\n   at System.Web.Mvc.ViewResultBase.ExecuteResult(ControllerContext context)\r\n   at System.Web.Mvc.ControllerActionInvoker.InvokeActionResultFilterRecursive(IList`1 filters, Int32 filterIndex, ResultExecutingContext preContext, ControllerContext controllerContext, ActionResult actionResult)\r\n   at System.Web.Mvc.ControllerActionInvoker.InvokeActionResultFilterRecursive(IList`1 filters, Int32 filterIndex, ResultExecutingContext preContext, ControllerContext controllerContext, ActionResult actionResult)\r\n   at System.Web.Mvc.ControllerActionInvoker.InvokeActionResultFilterRecursive(IList`1 filters, Int32 filterIndex, ResultExecutingContext preContext, ControllerContext controllerContext, ActionResult actionResult)\r\n   at System.Web.Mvc.ControllerActionInvoker.InvokeActionResultFilterRecursive(IList`1 filters, Int32 filterIndex, ResultExecutingContext preContext, ControllerContext controllerContext, ActionResult actionResult)\r\n   at System.Web.Mvc.ControllerActionInvoker.InvokeActionResultWithFilters(ControllerContext controllerContext, IList`1 filters, ActionResult actionResult)\r\n   at System.Web.Mvc.Async.AsyncControllerActionInvoker.<>c__DisplayClass3_1.<BeginInvokeAction>b__1(IAsyncResult asyncResult)\r\n   at System.Web.Mvc.Async.AsyncControllerActionInvoker.EndInvokeAction(IAsyncResult asyncResult)\r\n   at System.Web.Mvc.Controller.<>c.<BeginExecuteCore>b__152_1(IAsyncResult asyncResult, ExecuteCoreState innerState)\r\n   at System.Web.Mvc.Async.AsyncResultWrapper.WrappedAsyncVoid`1.CallEndDelegate(IAsyncResult asyncResult)\r\n   at System.Web.Mvc.Controller.EndExecuteCore(IAsyncResult asyncResult)\r\n   at System.Web.Mvc.Async.AsyncResultWrapper.WrappedAsyncVoid`1.CallEndDelegate(IAsyncResult asyncResult)\r\n   at System.Web.Mvc.Controller.EndExecute(IAsyncResult asyncResult)\r\n   at System.Web.Mvc.MvcHandler.<>c.<BeginProcessRequest>b__20_1(IAsyncResult asyncResult, ProcessRequestState innerState)\r\n   at System.Web.Mvc.Async.AsyncResultWrapper.WrappedAsyncVoid`1.CallEndDelegate(IAsyncResult asyncResult)\r\n   at System.Web.Mvc.MvcHandler.EndProcessRequest(IAsyncResult asyncResult)\r\n   at System.Web.HttpApplication.CallHandlerExecutionStep.System.Web.HttpApplication.IExecutionStep.Execute()\r\n   at System.Web.HttpApplication.ExecuteStepImpl(IExecutionStep step)\r\n   at System.Web.HttpApplication.ExecuteStep(IExecutionStep step, Boolean& completedSynchronously)","SourceContext":"Umbraco.Web.UmbracoApplicationBase","ProcessId":120252,"ProcessName":"w3wp","ThreadId":390,"AppDomainId":2,"AppDomainAppId":"LMW3SVC14ROOT","MachineName":"DESKTOP-3G1QN35","Log4NetLevel":"ERROR","HttpSessionId":"3oirk2aviuetil1mankawhyn","HttpRequestNumber":18,"HttpRequestId":"f0059997-36d0-4155-9e57-3591b8ebef30"}
{"@t":"2025-08-29T14:44:48.6581626Z","@mt":"An unhandled exception occurred","@l":"Error","@x":"System.NullReferenceException: Object reference not set to an instance of an object.\r\n   at TSPadel_Umbraco.Extensions.MediaHelper.GetUserPlatform(HttpRequest request) in C:\\Development\\TSPadel\\TSPadel_Umbraco\\Extensions\\MediaHelper.cs:line 152\r\n   at TSPadel_Umbraco.Extensions.MediaHelper.GetUserEnvironment(HttpRequest request) in C:\\Development\\TSPadel\\TSPadel_Umbraco\\Extensions\\MediaHelper.cs:line 144\r\n   at TSPadel_Umbraco.Extensions.MediaHelper.GetMediaURL(IPublishedContent contentItem, String propertyName, Int32 ImageWidth, HttpRequest request) in C:\\Development\\TSPadel\\TSPadel_Umbraco\\Extensions\\MediaHelper.cs:line 59\r\n   at ASP._Page_Views_Partials_Header_cshtml.Execute() in C:\\Development\\TSPadel\\TSPadel_Umbraco\\Views\\Partials\\Header.cshtml:line 59\r\n   at System.Web.WebPages.WebPageBase.ExecutePageHierarchy()\r\n   at System.Web.Mvc.WebViewPage.ExecutePageHierarchy()\r\n   at System.Web.WebPages.WebPageBase.ExecutePageHierarchy(WebPageContext pageContext, TextWriter writer, WebPageRenderingBase startPage)\r\n   at Umbraco.Web.Mvc.ProfilingView.Render(ViewContext viewContext, TextWriter writer) in D:\\a\\1\\s\\src\\Umbraco.Web\\Mvc\\ProfilingView.cs:line 25\r\n   at System.Web.Mvc.Html.PartialExtensions.Partial(HtmlHelper htmlHelper, String partialViewName, Object model, ViewDataDictionary viewData)\r\n   at ASP._Page_Views_Master_cshtml.Execute() in C:\\Development\\TSPadel\\TSPadel_Umbraco\\Views\\Master.cshtml:line 52\r\n   at System.Web.WebPages.WebPageBase.ExecutePageHierarchy()\r\n   at System.Web.Mvc.WebViewPage.ExecutePageHierarchy()\r\n   at System.Web.WebPages.WebPageBase.ExecutePageHierarchy(WebPageContext pageContext, TextWriter writer, WebPageRenderingBase startPage)\r\n   at System.Web.WebPages.WebPageBase.<>c__DisplayClass40_0.<RenderPageCore>b__0(TextWriter writer)\r\n   at System.Web.WebPages.WebPageBase.Write(HelperResult result)\r\n   at System.Web.WebPages.WebPageBase.RenderSurrounding(String partialViewName, Action`1 body)\r\n   at System.Web.WebPages.WebPageBase.PopContext()\r\n   at Umbraco.Web.Mvc.ProfilingView.Render(ViewContext viewContext, TextWriter writer) in D:\\a\\1\\s\\src\\Umbraco.Web\\Mvc\\ProfilingView.cs:line 25\r\n   at System.Web.Mvc.ViewResultBase.ExecuteResult(ControllerContext context)\r\n   at System.Web.Mvc.ControllerActionInvoker.InvokeActionResultFilterRecursive(IList`1 filters, Int32 filterIndex, ResultExecutingContext preContext, ControllerContext controllerContext, ActionResult actionResult)\r\n   at System.Web.Mvc.ControllerActionInvoker.InvokeActionResultFilterRecursive(IList`1 filters, Int32 filterIndex, ResultExecutingContext preContext, ControllerContext controllerContext, ActionResult actionResult)\r\n   at System.Web.Mvc.ControllerActionInvoker.InvokeActionResultFilterRecursive(IList`1 filters, Int32 filterIndex, ResultExecutingContext preContext, ControllerContext controllerContext, ActionResult actionResult)\r\n   at System.Web.Mvc.ControllerActionInvoker.InvokeActionResultFilterRecursive(IList`1 filters, Int32 filterIndex, ResultExecutingContext preContext, ControllerContext controllerContext, ActionResult actionResult)\r\n   at System.Web.Mvc.ControllerActionInvoker.InvokeActionResultWithFilters(ControllerContext controllerContext, IList`1 filters, ActionResult actionResult)\r\n   at System.Web.Mvc.Async.AsyncControllerActionInvoker.<>c__DisplayClass3_1.<BeginInvokeAction>b__1(IAsyncResult asyncResult)\r\n   at System.Web.Mvc.Async.AsyncControllerActionInvoker.EndInvokeAction(IAsyncResult asyncResult)\r\n   at System.Web.Mvc.Controller.<>c.<BeginExecuteCore>b__152_1(IAsyncResult asyncResult, ExecuteCoreState innerState)\r\n   at System.Web.Mvc.Async.AsyncResultWrapper.WrappedAsyncVoid`1.CallEndDelegate(IAsyncResult asyncResult)\r\n   at System.Web.Mvc.Controller.EndExecuteCore(IAsyncResult asyncResult)\r\n   at System.Web.Mvc.Async.AsyncResultWrapper.WrappedAsyncVoid`1.CallEndDelegate(IAsyncResult asyncResult)\r\n   at System.Web.Mvc.Controller.EndExecute(IAsyncResult asyncResult)\r\n   at System.Web.Mvc.MvcHandler.<>c.<BeginProcessRequest>b__20_1(IAsyncResult asyncResult, ProcessRequestState innerState)\r\n   at System.Web.Mvc.Async.AsyncResultWrapper.WrappedAsyncVoid`1.CallEndDelegate(IAsyncResult asyncResult)\r\n   at System.Web.Mvc.MvcHandler.EndProcessRequest(IAsyncResult asyncResult)\r\n   at System.Web.HttpApplication.CallHandlerExecutionStep.System.Web.HttpApplication.IExecutionStep.Execute()\r\n   at System.Web.HttpApplication.ExecuteStepImpl(IExecutionStep step)\r\n   at System.Web.HttpApplication.ExecuteStep(IExecutionStep step, Boolean& completedSynchronously)","SourceContext":"Umbraco.Web.UmbracoApplicationBase","ProcessId":120252,"ProcessName":"w3wp","ThreadId":710,"AppDomainId":2,"AppDomainAppId":"LMW3SVC14ROOT","MachineName":"DESKTOP-3G1QN35","Log4NetLevel":"ERROR","HttpSessionId":"f0h4q01cyyeq20w01p5hyzpl","HttpRequestNumber":19,"HttpRequestId":"c28700eb-643a-442a-a040-984006f0bc1c"}
{"@t":"2025-08-29T14:44:50.7370565Z","@mt":"Scheduled health check results:","SourceContext":"Umbraco.Web.HealthCheck.HealthCheckResults","ProcessId":120252,"ProcessName":"w3wp","ThreadId":163,"AppDomainId":2,"AppDomainAppId":"LMW3SVC14ROOT","MachineName":"DESKTOP-3G1QN35","Log4NetLevel":"INFO "}
{"@t":"2025-08-29T14:44:50.7370565Z","@mt":"Checks for '{HealthCheckName}' all completed successfully.","HealthCheckName":"Folder & File Permissions","SourceContext":"Umbraco.Web.HealthCheck.HealthCheckResults","ProcessId":120252,"ProcessName":"w3wp","ThreadId":163,"AppDomainId":2,"AppDomainAppId":"LMW3SVC14ROOT","MachineName":"DESKTOP-3G1QN35","Log4NetLevel":"INFO "}
{"@t":"2025-08-29T14:44:50.7370565Z","@mt":"Result for {HealthCheckName}: {HealthCheckResult}, Message: '{HealthCheckMessage}'","HealthCheckName":"Folder & File Permissions","HealthCheckResult":"Success","HealthCheckMessage":"All folders have the correct permissions set.","SourceContext":"Umbraco.Web.HealthCheck.HealthCheckResults","ProcessId":120252,"ProcessName":"w3wp","ThreadId":163,"AppDomainId":2,"AppDomainAppId":"LMW3SVC14ROOT","MachineName":"DESKTOP-3G1QN35","Log4NetLevel":"INFO "}
{"@t":"2025-08-29T14:44:50.7370565Z","@mt":"Result for {HealthCheckName}: {HealthCheckResult}, Message: '{HealthCheckMessage}'","HealthCheckName":"Folder & File Permissions","HealthCheckResult":"Success","HealthCheckMessage":"All files have the correct permissions set.","SourceContext":"Umbraco.Web.HealthCheck.HealthCheckResults","ProcessId":120252,"ProcessName":"w3wp","ThreadId":163,"AppDomainId":2,"AppDomainAppId":"LMW3SVC14ROOT","MachineName":"DESKTOP-3G1QN35","Log4NetLevel":"INFO "}
{"@t":"2025-08-29T14:44:50.7380566Z","@mt":"Checks for '{HealthCheckName}' completed with errors.","@l":"Warning","HealthCheckName":"SMTP Settings","SourceContext":"Umbraco.Web.HealthCheck.HealthCheckResults","ProcessId":120252,"ProcessName":"w3wp","ThreadId":163,"AppDomainId":2,"AppDomainAppId":"LMW3SVC14ROOT","MachineName":"DESKTOP-3G1QN35","Log4NetLevel":"WARN "}
{"@t":"2025-08-29T14:44:50.7380566Z","@mt":"Result for {HealthCheckName}: {HealthCheckResult}, Message: '{HealthCheckMessage}'","HealthCheckName":"SMTP Settings","HealthCheckResult":"Error","HealthCheckMessage":"In the Web.config file system.net/mailsettings section, the host is not configured.","SourceContext":"Umbraco.Web.HealthCheck.HealthCheckResults","ProcessId":120252,"ProcessName":"w3wp","ThreadId":163,"AppDomainId":2,"AppDomainAppId":"LMW3SVC14ROOT","MachineName":"DESKTOP-3G1QN35","Log4NetLevel":"INFO "}
{"@t":"2025-08-29T14:44:50.7380566Z","@mt":"Checks for '{HealthCheckName}' completed with errors.","@l":"Warning","HealthCheckName":"Application URL Configuration","SourceContext":"Umbraco.Web.HealthCheck.HealthCheckResults","ProcessId":120252,"ProcessName":"w3wp","ThreadId":163,"AppDomainId":2,"AppDomainAppId":"LMW3SVC14ROOT","MachineName":"DESKTOP-3G1QN35","Log4NetLevel":"WARN "}
{"@t":"2025-08-29T14:44:50.7380566Z","@mt":"Result for {HealthCheckName}: {HealthCheckResult}, Message: '{HealthCheckMessage}'","HealthCheckName":"Application URL Configuration","HealthCheckResult":"Warning","HealthCheckMessage":"The 'umbracoApplicationUrl' option is not set in your umbracoSettings.config file.","SourceContext":"Umbraco.Web.HealthCheck.HealthCheckResults","ProcessId":120252,"ProcessName":"w3wp","ThreadId":163,"AppDomainId":2,"AppDomainAppId":"LMW3SVC14ROOT","MachineName":"DESKTOP-3G1QN35","Log4NetLevel":"INFO "}
{"@t":"2025-08-29T14:44:50.7380566Z","@mt":"Checks for '{HealthCheckName}' completed with errors.","@l":"Warning","HealthCheckName":"Cross-site scripting Protection (X-XSS-Protection header)","SourceContext":"Umbraco.Web.HealthCheck.HealthCheckResults","ProcessId":120252,"ProcessName":"w3wp","ThreadId":163,"AppDomainId":2,"AppDomainAppId":"LMW3SVC14ROOT","MachineName":"DESKTOP-3G1QN35","Log4NetLevel":"WARN "}
{"@t":"2025-08-29T14:44:50.7380566Z","@mt":"Result for {HealthCheckName}: {HealthCheckResult}, Message: '{HealthCheckMessage}'","HealthCheckName":"Cross-site scripting Protection (X-XSS-Protection header)","HealthCheckResult":"Error","HealthCheckMessage":"Error pinging the URL http://localhost.tspadel.co.uk - 'The remote server returned an error: (500) Internal Server Error.'","SourceContext":"Umbraco.Web.HealthCheck.HealthCheckResults","ProcessId":120252,"ProcessName":"w3wp","ThreadId":163,"AppDomainId":2,"AppDomainAppId":"LMW3SVC14ROOT","MachineName":"DESKTOP-3G1QN35","Log4NetLevel":"INFO "}
{"@t":"2025-08-29T14:44:50.7380566Z","@mt":"Checks for '{HealthCheckName}' completed with errors.","@l":"Warning","HealthCheckName":"Cookie hijacking and protocol downgrade attacks Protection (Strict-Transport-Security Header (HSTS))","SourceContext":"Umbraco.Web.HealthCheck.HealthCheckResults","ProcessId":120252,"ProcessName":"w3wp","ThreadId":163,"AppDomainId":2,"AppDomainAppId":"LMW3SVC14ROOT","MachineName":"DESKTOP-3G1QN35","Log4NetLevel":"WARN "}
{"@t":"2025-08-29T14:44:50.7380566Z","@mt":"Result for {HealthCheckName}: {HealthCheckResult}, Message: '{HealthCheckMessage}'","HealthCheckName":"Cookie hijacking and protocol downgrade attacks Protection (Strict-Transport-Security Header (HSTS))","HealthCheckResult":"Error","HealthCheckMessage":"Error pinging the URL http://localhost.tspadel.co.uk - 'The remote server returned an error: (500) Internal Server Error.'","SourceContext":"Umbraco.Web.HealthCheck.HealthCheckResults","ProcessId":120252,"ProcessName":"w3wp","ThreadId":163,"AppDomainId":2,"AppDomainAppId":"LMW3SVC14ROOT","MachineName":"DESKTOP-3G1QN35","Log4NetLevel":"INFO "}
{"@t":"2025-08-29T14:44:50.7380566Z","@mt":"Checks for '{HealthCheckName}' completed with errors.","@l":"Warning","HealthCheckName":"Content/MIME Sniffing Protection","SourceContext":"Umbraco.Web.HealthCheck.HealthCheckResults","ProcessId":120252,"ProcessName":"w3wp","ThreadId":163,"AppDomainId":2,"AppDomainAppId":"LMW3SVC14ROOT","MachineName":"DESKTOP-3G1QN35","Log4NetLevel":"WARN "}
{"@t":"2025-08-29T14:44:50.7380566Z","@mt":"Result for {HealthCheckName}: {HealthCheckResult}, Message: '{HealthCheckMessage}'","HealthCheckName":"Content/MIME Sniffing Protection","HealthCheckResult":"Error","HealthCheckMessage":"Error pinging the URL http://localhost.tspadel.co.uk - 'The remote server returned an error: (500) Internal Server Error.'","SourceContext":"Umbraco.Web.HealthCheck.HealthCheckResults","ProcessId":120252,"ProcessName":"w3wp","ThreadId":163,"AppDomainId":2,"AppDomainAppId":"LMW3SVC14ROOT","MachineName":"DESKTOP-3G1QN35","Log4NetLevel":"INFO "}
{"@t":"2025-08-29T14:44:50.7380566Z","@mt":"Checks for '{HealthCheckName}' completed with errors.","@l":"Warning","HealthCheckName":"Excessive Headers","SourceContext":"Umbraco.Web.HealthCheck.HealthCheckResults","ProcessId":120252,"ProcessName":"w3wp","ThreadId":163,"AppDomainId":2,"AppDomainAppId":"LMW3SVC14ROOT","MachineName":"DESKTOP-3G1QN35","Log4NetLevel":"WARN "}
{"@t":"2025-08-29T14:44:50.7380566Z","@mt":"Result for {HealthCheckName}: {HealthCheckResult}, Message: '{HealthCheckMessage}'","HealthCheckName":"Excessive Headers","HealthCheckResult":"Warning","HealthCheckMessage":"Error pinging the URL http://localhost.tspadel.co.uk - 'The remote server returned an error: (500) Internal Server Error.'","SourceContext":"Umbraco.Web.HealthCheck.HealthCheckResults","ProcessId":120252,"ProcessName":"w3wp","ThreadId":163,"AppDomainId":2,"AppDomainAppId":"LMW3SVC14ROOT","MachineName":"DESKTOP-3G1QN35","Log4NetLevel":"INFO "}
{"@t":"2025-08-29T14:44:50.7380566Z","@mt":"Checks for '{HealthCheckName}' completed with errors.","@l":"Warning","HealthCheckName":"Click-Jacking Protection","SourceContext":"Umbraco.Web.HealthCheck.HealthCheckResults","ProcessId":120252,"ProcessName":"w3wp","ThreadId":163,"AppDomainId":2,"AppDomainAppId":"LMW3SVC14ROOT","MachineName":"DESKTOP-3G1QN35","Log4NetLevel":"WARN "}
{"@t":"2025-08-29T14:44:50.7380566Z","@mt":"Result for {HealthCheckName}: {HealthCheckResult}, Message: '{HealthCheckMessage}'","HealthCheckName":"Click-Jacking Protection","HealthCheckResult":"Error","HealthCheckMessage":"Error pinging the URL http://localhost.tspadel.co.uk - 'The remote server returned an error: (500) Internal Server Error.'","SourceContext":"Umbraco.Web.HealthCheck.HealthCheckResults","ProcessId":120252,"ProcessName":"w3wp","ThreadId":163,"AppDomainId":2,"AppDomainAppId":"LMW3SVC14ROOT","MachineName":"DESKTOP-3G1QN35","Log4NetLevel":"INFO "}
{"@t":"2025-08-29T14:44:50.7380566Z","@mt":"Checks for '{HealthCheckName}' completed with errors.","@l":"Warning","HealthCheckName":"HTTPS Configuration","SourceContext":"Umbraco.Web.HealthCheck.HealthCheckResults","ProcessId":120252,"ProcessName":"w3wp","ThreadId":163,"AppDomainId":2,"AppDomainAppId":"LMW3SVC14ROOT","MachineName":"DESKTOP-3G1QN35","Log4NetLevel":"WARN "}
{"@t":"2025-08-29T14:44:50.7380566Z","@mt":"Result for {HealthCheckName}: {HealthCheckResult}, Message: '{HealthCheckMessage}'","HealthCheckName":"HTTPS Configuration","HealthCheckResult":"Error","HealthCheckMessage":"You are currently not viewing the site using the HTTPS scheme.","SourceContext":"Umbraco.Web.HealthCheck.HealthCheckResults","ProcessId":120252,"ProcessName":"w3wp","ThreadId":163,"AppDomainId":2,"AppDomainAppId":"LMW3SVC14ROOT","MachineName":"DESKTOP-3G1QN35","Log4NetLevel":"INFO "}
{"@t":"2025-08-29T14:44:50.7380566Z","@mt":"Result for {HealthCheckName}: {HealthCheckResult}, Message: '{HealthCheckMessage}'","HealthCheckName":"HTTPS Configuration","HealthCheckResult":"Info","HealthCheckMessage":"The appSetting 'Umbraco.Core.UseHttps' is set to 'false' in your web.config file. Once you access this site using the HTTPS scheme, that should be set to 'true'.","SourceContext":"Umbraco.Web.HealthCheck.HealthCheckResults","ProcessId":120252,"ProcessName":"w3wp","ThreadId":163,"AppDomainId":2,"AppDomainAppId":"LMW3SVC14ROOT","MachineName":"DESKTOP-3G1QN35","Log4NetLevel":"INFO "}
{"@t":"2025-08-29T14:44:50.7380566Z","@mt":"Result for {HealthCheckName}: {HealthCheckResult}, Message: '{HealthCheckMessage}'","HealthCheckName":"HTTPS Configuration","HealthCheckResult":"Error","HealthCheckMessage":"Error pinging the URL https://localhost.tspadel.co.uk/umbraco - 'Unable to connect to the remote server'","SourceContext":"Umbraco.Web.HealthCheck.HealthCheckResults","ProcessId":120252,"ProcessName":"w3wp","ThreadId":163,"AppDomainId":2,"AppDomainAppId":"LMW3SVC14ROOT","MachineName":"DESKTOP-3G1QN35","Log4NetLevel":"INFO "}
{"@t":"2025-08-29T14:44:50.7380566Z","@mt":"Checks for '{HealthCheckName}' all completed successfully.","HealthCheckName":"Database data integrity check","SourceContext":"Umbraco.Web.HealthCheck.HealthCheckResults","ProcessId":120252,"ProcessName":"w3wp","ThreadId":163,"AppDomainId":2,"AppDomainAppId":"LMW3SVC14ROOT","MachineName":"DESKTOP-3G1QN35","Log4NetLevel":"INFO "}
{"@t":"2025-08-29T14:44:50.7380566Z","@mt":"Result for {HealthCheckName}: {HealthCheckResult}, Message: '{HealthCheckMessage}'","HealthCheckName":"Database data integrity check","HealthCheckResult":"Success","HealthCheckMessage":"<p>All document paths are valid</p>\r\n","SourceContext":"Umbraco.Web.HealthCheck.HealthCheckResults","ProcessId":120252,"ProcessName":"w3wp","ThreadId":163,"AppDomainId":2,"AppDomainAppId":"LMW3SVC14ROOT","MachineName":"DESKTOP-3G1QN35","Log4NetLevel":"INFO "}
{"@t":"2025-08-29T14:44:50.7380566Z","@mt":"Result for {HealthCheckName}: {HealthCheckResult}, Message: '{HealthCheckMessage}'","HealthCheckName":"Database data integrity check","HealthCheckResult":"Success","HealthCheckMessage":"<p>All media paths are valid</p>\r\n","SourceContext":"Umbraco.Web.HealthCheck.HealthCheckResults","ProcessId":120252,"ProcessName":"w3wp","ThreadId":163,"AppDomainId":2,"AppDomainAppId":"LMW3SVC14ROOT","MachineName":"DESKTOP-3G1QN35","Log4NetLevel":"INFO "}
{"@t":"2025-08-29T14:44:50.7380566Z","@mt":"Checks for '{HealthCheckName}' completed with errors.","@l":"Warning","HealthCheckName":"Macro errors","SourceContext":"Umbraco.Web.HealthCheck.HealthCheckResults","ProcessId":120252,"ProcessName":"w3wp","ThreadId":163,"AppDomainId":2,"AppDomainAppId":"LMW3SVC14ROOT","MachineName":"DESKTOP-3G1QN35","Log4NetLevel":"WARN "}
{"@t":"2025-08-29T14:44:50.7380566Z","@mt":"Result for {HealthCheckName}: {HealthCheckResult}, Message: '{HealthCheckMessage}'","HealthCheckName":"Macro errors","HealthCheckResult":"Error","HealthCheckMessage":"MacroErrors are set to 'throw' which will prevent some or all pages in your site from loading completely if there are any errors in macros. Rectifying this will set the value to 'inline'.","SourceContext":"Umbraco.Web.HealthCheck.HealthCheckResults","ProcessId":120252,"ProcessName":"w3wp","ThreadId":163,"AppDomainId":2,"AppDomainAppId":"LMW3SVC14ROOT","MachineName":"DESKTOP-3G1QN35","Log4NetLevel":"INFO "}
{"@t":"2025-08-29T14:44:50.7380566Z","@mt":"Checks for '{HealthCheckName}' completed with errors.","@l":"Warning","HealthCheckName":"Notification Email Settings","SourceContext":"Umbraco.Web.HealthCheck.HealthCheckResults","ProcessId":120252,"ProcessName":"w3wp","ThreadId":163,"AppDomainId":2,"AppDomainAppId":"LMW3SVC14ROOT","MachineName":"DESKTOP-3G1QN35","Log4NetLevel":"WARN "}
{"@t":"2025-08-29T14:44:50.7380566Z","@mt":"Result for {HealthCheckName}: {HealthCheckResult}, Message: '{HealthCheckMessage}'","HealthCheckName":"Notification Email Settings","HealthCheckResult":"Error","HealthCheckMessage":"Notification email is still set to the default value of <strong>your@email.here</strong>.","SourceContext":"Umbraco.Web.HealthCheck.HealthCheckResults","ProcessId":120252,"ProcessName":"w3wp","ThreadId":163,"AppDomainId":2,"AppDomainAppId":"LMW3SVC14ROOT","MachineName":"DESKTOP-3G1QN35","Log4NetLevel":"INFO "}
{"@t":"2025-08-29T14:44:50.7380566Z","@mt":"Checks for '{HealthCheckName}' all completed successfully.","HealthCheckName":"Try Skip IIS Custom Errors","SourceContext":"Umbraco.Web.HealthCheck.HealthCheckResults","ProcessId":120252,"ProcessName":"w3wp","ThreadId":163,"AppDomainId":2,"AppDomainAppId":"LMW3SVC14ROOT","MachineName":"DESKTOP-3G1QN35","Log4NetLevel":"INFO "}
{"@t":"2025-08-29T14:44:50.7380566Z","@mt":"Result for {HealthCheckName}: {HealthCheckResult}, Message: '{HealthCheckMessage}'","HealthCheckName":"Try Skip IIS Custom Errors","HealthCheckResult":"Success","HealthCheckMessage":"Try Skip IIS Custom Errors is set to 'true' and you're using IIS version '10.0'.","SourceContext":"Umbraco.Web.HealthCheck.HealthCheckResults","ProcessId":120252,"ProcessName":"w3wp","ThreadId":163,"AppDomainId":2,"AppDomainAppId":"LMW3SVC14ROOT","MachineName":"DESKTOP-3G1QN35","Log4NetLevel":"INFO "}
{"@t":"2025-08-29T14:44:50.7380566Z","@mt":"Checks for '{HealthCheckName}' all completed successfully.","HealthCheckName":"Custom Errors","SourceContext":"Umbraco.Web.HealthCheck.HealthCheckResults","ProcessId":120252,"ProcessName":"w3wp","ThreadId":163,"AppDomainId":2,"AppDomainAppId":"LMW3SVC14ROOT","MachineName":"DESKTOP-3G1QN35","Log4NetLevel":"INFO "}
{"@t":"2025-08-29T14:44:50.7380566Z","@mt":"Result for {HealthCheckName}: {HealthCheckResult}, Message: '{HealthCheckMessage}'","HealthCheckName":"Custom Errors","HealthCheckResult":"Success","HealthCheckMessage":"Custom errors are set to 'RemoteOnly'.","SourceContext":"Umbraco.Web.HealthCheck.HealthCheckResults","ProcessId":120252,"ProcessName":"w3wp","ThreadId":163,"AppDomainId":2,"AppDomainAppId":"LMW3SVC14ROOT","MachineName":"DESKTOP-3G1QN35","Log4NetLevel":"INFO "}
{"@t":"2025-08-29T14:44:50.7380566Z","@mt":"Checks for '{HealthCheckName}' all completed successfully.","HealthCheckName":"Trace Mode","SourceContext":"Umbraco.Web.HealthCheck.HealthCheckResults","ProcessId":120252,"ProcessName":"w3wp","ThreadId":163,"AppDomainId":2,"AppDomainAppId":"LMW3SVC14ROOT","MachineName":"DESKTOP-3G1QN35","Log4NetLevel":"INFO "}
{"@t":"2025-08-29T14:44:50.7380566Z","@mt":"Result for {HealthCheckName}: {HealthCheckResult}, Message: '{HealthCheckMessage}'","HealthCheckName":"Trace Mode","HealthCheckResult":"Success","HealthCheckMessage":"Trace mode is disabled.","SourceContext":"Umbraco.Web.HealthCheck.HealthCheckResults","ProcessId":120252,"ProcessName":"w3wp","ThreadId":163,"AppDomainId":2,"AppDomainAppId":"LMW3SVC14ROOT","MachineName":"DESKTOP-3G1QN35","Log4NetLevel":"INFO "}
{"@t":"2025-08-29T14:44:50.7380566Z","@mt":"Checks for '{HealthCheckName}' completed with errors.","@l":"Warning","HealthCheckName":"Debug Compilation Mode","SourceContext":"Umbraco.Web.HealthCheck.HealthCheckResults","ProcessId":120252,"ProcessName":"w3wp","ThreadId":163,"AppDomainId":2,"AppDomainAppId":"LMW3SVC14ROOT","MachineName":"DESKTOP-3G1QN35","Log4NetLevel":"WARN "}
{"@t":"2025-08-29T14:44:50.7380566Z","@mt":"Result for {HealthCheckName}: {HealthCheckResult}, Message: '{HealthCheckMessage}'","HealthCheckName":"Debug Compilation Mode","HealthCheckResult":"Error","HealthCheckMessage":"Debug compilation mode is currently enabled. It is recommended to disable this setting before go live.","SourceContext":"Umbraco.Web.HealthCheck.HealthCheckResults","ProcessId":120252,"ProcessName":"w3wp","ThreadId":163,"AppDomainId":2,"AppDomainAppId":"LMW3SVC14ROOT","MachineName":"DESKTOP-3G1QN35","Log4NetLevel":"INFO "}
{"@t":"2025-08-29T19:41:42.7556789Z","@mt":"{LogPrefix} Terminating {Immediate}","LogPrefix":"[ServerInstProcess] ","Immediate":"","SourceContext":"Umbraco.Web.Scheduling.BackgroundTaskRunner","ProcessId":120252,"ProcessName":"w3wp","ThreadId":408,"AppDomainId":2,"AppDomainAppId":"LMW3SVC14ROOT","MachineName":"DESKTOP-3G1QN35","Log4NetLevel":"INFO "}
{"@t":"2025-08-29T19:41:42.7616780Z","@mt":"Stopping ({SignalSource})","SignalSource":"environment","SourceContext":"Umbraco.Core.Runtime.MainDom","ProcessId":120252,"ProcessName":"w3wp","ThreadId":408,"AppDomainId":2,"AppDomainAppId":"LMW3SVC14ROOT","MachineName":"DESKTOP-3G1QN35","Log4NetLevel":"INFO "}
{"@t":"2025-08-29T19:41:42.7647812Z","@mt":"{LogPrefix} Canceling tasks","LogPrefix":"[ServerInstProcess] ","SourceContext":"Umbraco.Web.Scheduling.BackgroundTaskRunner","ProcessId":120252,"ProcessName":"w3wp","ThreadId":574,"AppDomainId":2,"AppDomainAppId":"LMW3SVC14ROOT","MachineName":"DESKTOP-3G1QN35","Log4NetLevel":"INFO "}
{"@t":"2025-08-29T19:41:42.7657811Z","@mt":"{LogPrefix} Tasks {TaskStatus}, terminated","LogPrefix":"[ServerInstProcess] ","TaskStatus":"cancelled","SourceContext":"Umbraco.Web.Scheduling.BackgroundTaskRunner","ProcessId":120252,"ProcessName":"w3wp","ThreadId":574,"AppDomainId":2,"AppDomainAppId":"LMW3SVC14ROOT","MachineName":"DESKTOP-3G1QN35","Log4NetLevel":"INFO "}
{"@t":"2025-08-29T19:41:42.7697811Z","@mt":"{StartMessage} [Timing {TimingId}]","StartMessage":"Examine shutting down","TimingId":"d75080d","SourceContext":"Umbraco.Web.Search.ExamineComponent","ProcessId":120252,"ProcessName":"w3wp","ThreadId":408,"AppDomainId":2,"AppDomainAppId":"LMW3SVC14ROOT","MachineName":"DESKTOP-3G1QN35","Log4NetLevel":"INFO "}
{"@t":"2025-08-29T19:41:42.7857854Z","@mt":"{EndMessage} ({Duration}ms) [Timing {TimingId}]","EndMessage":"Completed.","Duration":15,"TimingId":"d75080d","SourceContext":"Umbraco.Web.Search.ExamineComponent","ProcessId":120252,"ProcessName":"w3wp","ThreadId":408,"AppDomainId":2,"AppDomainAppId":"LMW3SVC14ROOT","MachineName":"DESKTOP-3G1QN35","Log4NetLevel":"INFO "}
{"@t":"2025-08-29T19:41:42.8142927Z","@mt":"Released from MainDom","SourceContext":"Umbraco.Web.PublishedCache.NuCache.PublishedSnapshotService","ProcessId":120252,"ProcessName":"w3wp","ThreadId":408,"AppDomainId":2,"AppDomainAppId":"LMW3SVC14ROOT","MachineName":"DESKTOP-3G1QN35","Log4NetLevel":"INFO "}
{"@t":"2025-08-29T19:41:42.8162920Z","@mt":"Released ({SignalSource})","SignalSource":"environment","SourceContext":"Umbraco.Core.Runtime.MainDom","ProcessId":120252,"ProcessName":"w3wp","ThreadId":408,"AppDomainId":2,"AppDomainAppId":"LMW3SVC14ROOT","MachineName":"DESKTOP-3G1QN35","Log4NetLevel":"INFO "}
{"@t":"2025-08-29T19:41:42.8162920Z","@mt":"{LogPrefix} Terminating {Immediate}","LogPrefix":"[KeepAlive] ","Immediate":"","SourceContext":"Umbraco.Web.Scheduling.BackgroundTaskRunner","ProcessId":120252,"ProcessName":"w3wp","ThreadId":408,"AppDomainId":2,"AppDomainAppId":"LMW3SVC14ROOT","MachineName":"DESKTOP-3G1QN35","Log4NetLevel":"INFO "}
{"@t":"2025-08-29T19:41:42.8162920Z","@mt":"{LogPrefix} Terminating {Immediate}","LogPrefix":"[ScheduledTasks] ","Immediate":"","SourceContext":"Umbraco.Web.Scheduling.BackgroundTaskRunner","ProcessId":120252,"ProcessName":"w3wp","ThreadId":408,"AppDomainId":2,"AppDomainAppId":"LMW3SVC14ROOT","MachineName":"DESKTOP-3G1QN35","Log4NetLevel":"INFO "}
{"@t":"2025-08-29T19:41:42.8162920Z","@mt":"{LogPrefix} Terminating {Immediate}","LogPrefix":"[RebuildIndexesOnStartup] ","Immediate":"","SourceContext":"Umbraco.Web.Scheduling.BackgroundTaskRunner","ProcessId":120252,"ProcessName":"w3wp","ThreadId":408,"AppDomainId":2,"AppDomainAppId":"LMW3SVC14ROOT","MachineName":"DESKTOP-3G1QN35","Log4NetLevel":"INFO "}
{"@t":"2025-08-29T19:41:42.8162920Z","@mt":"{LogPrefix} Terminating {Immediate}","LogPrefix":"[ServerRegistration] ","Immediate":"","SourceContext":"Umbraco.Web.Scheduling.BackgroundTaskRunner","ProcessId":120252,"ProcessName":"w3wp","ThreadId":408,"AppDomainId":2,"AppDomainAppId":"LMW3SVC14ROOT","MachineName":"DESKTOP-3G1QN35","Log4NetLevel":"INFO "}
{"@t":"2025-08-29T19:41:42.8162920Z","@mt":"{LogPrefix} Terminating {Immediate}","LogPrefix":"[LogScrubber] ","Immediate":"","SourceContext":"Umbraco.Web.Scheduling.BackgroundTaskRunner","ProcessId":120252,"ProcessName":"w3wp","ThreadId":408,"AppDomainId":2,"AppDomainAppId":"LMW3SVC14ROOT","MachineName":"DESKTOP-3G1QN35","Log4NetLevel":"INFO "}
{"@t":"2025-08-29T19:41:42.8162920Z","@mt":"{LogPrefix} Canceling tasks","LogPrefix":"[ScheduledTasks] ","SourceContext":"Umbraco.Web.Scheduling.BackgroundTaskRunner","ProcessId":120252,"ProcessName":"w3wp","ThreadId":132,"AppDomainId":2,"AppDomainAppId":"LMW3SVC14ROOT","MachineName":"DESKTOP-3G1QN35","Log4NetLevel":"INFO "}
{"@t":"2025-08-29T19:41:42.8162920Z","@mt":"{LogPrefix} Tasks {TaskStatus}, terminated","LogPrefix":"[ScheduledTasks] ","TaskStatus":"cancelled","SourceContext":"Umbraco.Web.Scheduling.BackgroundTaskRunner","ProcessId":120252,"ProcessName":"w3wp","ThreadId":132,"AppDomainId":2,"AppDomainAppId":"LMW3SVC14ROOT","MachineName":"DESKTOP-3G1QN35","Log4NetLevel":"INFO "}
{"@t":"2025-08-29T19:41:42.8162920Z","@mt":"{LogPrefix} Terminating {Immediate}","LogPrefix":"[ContentVersionCleanup] ","Immediate":"","SourceContext":"Umbraco.Web.Scheduling.BackgroundTaskRunner","ProcessId":120252,"ProcessName":"w3wp","ThreadId":408,"AppDomainId":2,"AppDomainAppId":"LMW3SVC14ROOT","MachineName":"DESKTOP-3G1QN35","Log4NetLevel":"INFO "}
{"@t":"2025-08-29T19:41:42.8162920Z","@mt":"{LogPrefix} Canceling tasks","LogPrefix":"[RebuildIndexesOnStartup] ","SourceContext":"Umbraco.Web.Scheduling.BackgroundTaskRunner","ProcessId":120252,"ProcessName":"w3wp","ThreadId":400,"AppDomainId":2,"AppDomainAppId":"LMW3SVC14ROOT","MachineName":"DESKTOP-3G1QN35","Log4NetLevel":"INFO "}
{"@t":"2025-08-29T19:41:42.8162920Z","@mt":"{LogPrefix} Terminating {Immediate}","LogPrefix":"[HealthCheckNotifier] ","Immediate":"","SourceContext":"Umbraco.Web.Scheduling.BackgroundTaskRunner","ProcessId":120252,"ProcessName":"w3wp","ThreadId":408,"AppDomainId":2,"AppDomainAppId":"LMW3SVC14ROOT","MachineName":"DESKTOP-3G1QN35","Log4NetLevel":"INFO "}
{"@t":"2025-08-29T19:41:42.8162920Z","@mt":"{LogPrefix} Tasks {TaskStatus}, terminated","LogPrefix":"[RebuildIndexesOnStartup] ","TaskStatus":"cancelled","SourceContext":"Umbraco.Web.Scheduling.BackgroundTaskRunner","ProcessId":120252,"ProcessName":"w3wp","ThreadId":400,"AppDomainId":2,"AppDomainAppId":"LMW3SVC14ROOT","MachineName":"DESKTOP-3G1QN35","Log4NetLevel":"INFO "}
{"@t":"2025-08-29T19:41:42.8162920Z","@mt":"{LogPrefix} Canceling tasks","LogPrefix":"[KeepAlive] ","SourceContext":"Umbraco.Web.Scheduling.BackgroundTaskRunner","ProcessId":120252,"ProcessName":"w3wp","ThreadId":660,"AppDomainId":2,"AppDomainAppId":"LMW3SVC14ROOT","MachineName":"DESKTOP-3G1QN35","Log4NetLevel":"INFO "}
{"@t":"2025-08-29T19:41:42.8162920Z","@mt":"{LogPrefix} Tasks {TaskStatus}, terminated","LogPrefix":"[KeepAlive] ","TaskStatus":"cancelled","SourceContext":"Umbraco.Web.Scheduling.BackgroundTaskRunner","ProcessId":120252,"ProcessName":"w3wp","ThreadId":660,"AppDomainId":2,"AppDomainAppId":"LMW3SVC14ROOT","MachineName":"DESKTOP-3G1QN35","Log4NetLevel":"INFO "}
{"@t":"2025-08-29T19:41:42.8162920Z","@mt":"{LogPrefix} Canceling tasks","LogPrefix":"[HealthCheckNotifier] ","SourceContext":"Umbraco.Web.Scheduling.BackgroundTaskRunner","ProcessId":120252,"ProcessName":"w3wp","ThreadId":374,"AppDomainId":2,"AppDomainAppId":"LMW3SVC14ROOT","MachineName":"DESKTOP-3G1QN35","Log4NetLevel":"INFO "}
{"@t":"2025-08-29T19:41:42.8162920Z","@mt":"{LogPrefix} Canceling tasks","LogPrefix":"[ServerRegistration] ","SourceContext":"Umbraco.Web.Scheduling.BackgroundTaskRunner","ProcessId":120252,"ProcessName":"w3wp","ThreadId":409,"AppDomainId":2,"AppDomainAppId":"LMW3SVC14ROOT","MachineName":"DESKTOP-3G1QN35","Log4NetLevel":"INFO "}
{"@t":"2025-08-29T19:41:42.8162920Z","@mt":"{LogPrefix} Tasks {TaskStatus}, terminated","LogPrefix":"[HealthCheckNotifier] ","TaskStatus":"cancelled","SourceContext":"Umbraco.Web.Scheduling.BackgroundTaskRunner","ProcessId":120252,"ProcessName":"w3wp","ThreadId":374,"AppDomainId":2,"AppDomainAppId":"LMW3SVC14ROOT","MachineName":"DESKTOP-3G1QN35","Log4NetLevel":"INFO "}
{"@t":"2025-08-29T19:41:42.8162920Z","@mt":"{LogPrefix} Canceling tasks","LogPrefix":"[LogScrubber] ","SourceContext":"Umbraco.Web.Scheduling.BackgroundTaskRunner","ProcessId":120252,"ProcessName":"w3wp","ThreadId":54,"AppDomainId":2,"AppDomainAppId":"LMW3SVC14ROOT","MachineName":"DESKTOP-3G1QN35","Log4NetLevel":"INFO "}
{"@t":"2025-08-29T19:41:42.8162920Z","@mt":"{LogPrefix} Tasks {TaskStatus}, terminated","LogPrefix":"[ServerRegistration] ","TaskStatus":"cancelled","SourceContext":"Umbraco.Web.Scheduling.BackgroundTaskRunner","ProcessId":120252,"ProcessName":"w3wp","ThreadId":409,"AppDomainId":2,"AppDomainAppId":"LMW3SVC14ROOT","MachineName":"DESKTOP-3G1QN35","Log4NetLevel":"INFO "}
{"@t":"2025-08-29T19:41:42.8162920Z","@mt":"{LogPrefix} Tasks {TaskStatus}, terminated","LogPrefix":"[LogScrubber] ","TaskStatus":"cancelled","SourceContext":"Umbraco.Web.Scheduling.BackgroundTaskRunner","ProcessId":120252,"ProcessName":"w3wp","ThreadId":54,"AppDomainId":2,"AppDomainAppId":"LMW3SVC14ROOT","MachineName":"DESKTOP-3G1QN35","Log4NetLevel":"INFO "}
{"@t":"2025-08-29T19:41:42.8162920Z","@mt":"{LogPrefix} Canceling tasks","LogPrefix":"[ContentVersionCleanup] ","SourceContext":"Umbraco.Web.Scheduling.BackgroundTaskRunner","ProcessId":120252,"ProcessName":"w3wp","ThreadId":660,"AppDomainId":2,"AppDomainAppId":"LMW3SVC14ROOT","MachineName":"DESKTOP-3G1QN35","Log4NetLevel":"INFO "}
{"@t":"2025-08-29T19:41:42.8162920Z","@mt":"{LogPrefix} Tasks {TaskStatus}, terminated","LogPrefix":"[ContentVersionCleanup] ","TaskStatus":"cancelled","SourceContext":"Umbraco.Web.Scheduling.BackgroundTaskRunner","ProcessId":120252,"ProcessName":"w3wp","ThreadId":660,"AppDomainId":2,"AppDomainAppId":"LMW3SVC14ROOT","MachineName":"DESKTOP-3G1QN35","Log4NetLevel":"INFO "}
{"@t":"2025-08-29T19:41:42.8172920Z","@mt":"{LogPrefix} Terminating {Immediate}","LogPrefix":"[TelemetryReporter] ","Immediate":"","SourceContext":"Umbraco.Web.Scheduling.BackgroundTaskRunner","ProcessId":120252,"ProcessName":"w3wp","ThreadId":408,"AppDomainId":2,"AppDomainAppId":"LMW3SVC14ROOT","MachineName":"DESKTOP-3G1QN35","Log4NetLevel":"INFO "}
{"@t":"2025-08-29T19:41:42.8172920Z","@mt":"{LogPrefix} Canceling tasks","LogPrefix":"[TelemetryReporter] ","SourceContext":"Umbraco.Web.Scheduling.BackgroundTaskRunner","ProcessId":120252,"ProcessName":"w3wp","ThreadId":144,"AppDomainId":2,"AppDomainAppId":"LMW3SVC14ROOT","MachineName":"DESKTOP-3G1QN35","Log4NetLevel":"INFO "}
{"@t":"2025-08-29T19:41:42.8172920Z","@mt":"{LogPrefix} Tasks {TaskStatus}, terminated","LogPrefix":"[TelemetryReporter] ","TaskStatus":"cancelled","SourceContext":"Umbraco.Web.Scheduling.BackgroundTaskRunner","ProcessId":120252,"ProcessName":"w3wp","ThreadId":144,"AppDomainId":2,"AppDomainAppId":"LMW3SVC14ROOT","MachineName":"DESKTOP-3G1QN35","Log4NetLevel":"INFO "}
{"@t":"2025-08-29T19:41:42.8202921Z","@mt":"{LogPrefix} Terminating {Immediate}","LogPrefix":"[TempFileCleanup] ","Immediate":"","SourceContext":"Umbraco.Web.Scheduling.BackgroundTaskRunner","ProcessId":120252,"ProcessName":"w3wp","ThreadId":408,"AppDomainId":2,"AppDomainAppId":"LMW3SVC14ROOT","MachineName":"DESKTOP-3G1QN35","Log4NetLevel":"INFO "}
{"@t":"2025-08-29T19:41:42.8202921Z","@mt":"{LogPrefix} Terminating {Immediate}","LogPrefix":"[ScheduledPublishing] ","Immediate":"","SourceContext":"Umbraco.Web.Scheduling.BackgroundTaskRunner","ProcessId":120252,"ProcessName":"w3wp","ThreadId":408,"AppDomainId":2,"AppDomainAppId":"LMW3SVC14ROOT","MachineName":"DESKTOP-3G1QN35","Log4NetLevel":"INFO "}
{"@t":"2025-08-29T19:41:42.8202921Z","@mt":"{LogPrefix} Canceling tasks","LogPrefix":"[TempFileCleanup] ","SourceContext":"Umbraco.Web.Scheduling.BackgroundTaskRunner","ProcessId":120252,"ProcessName":"w3wp","ThreadId":374,"AppDomainId":2,"AppDomainAppId":"LMW3SVC14ROOT","MachineName":"DESKTOP-3G1QN35","Log4NetLevel":"INFO "}
{"@t":"2025-08-29T19:41:42.8202921Z","@mt":"{LogPrefix} Canceling tasks","LogPrefix":"[ScheduledPublishing] ","SourceContext":"Umbraco.Web.Scheduling.BackgroundTaskRunner","ProcessId":120252,"ProcessName":"w3wp","ThreadId":660,"AppDomainId":2,"AppDomainAppId":"LMW3SVC14ROOT","MachineName":"DESKTOP-3G1QN35","Log4NetLevel":"INFO "}
{"@t":"2025-08-29T19:41:42.8202921Z","@mt":"{LogPrefix} Tasks {TaskStatus}, terminated","LogPrefix":"[TempFileCleanup] ","TaskStatus":"cancelled","SourceContext":"Umbraco.Web.Scheduling.BackgroundTaskRunner","ProcessId":120252,"ProcessName":"w3wp","ThreadId":374,"AppDomainId":2,"AppDomainAppId":"LMW3SVC14ROOT","MachineName":"DESKTOP-3G1QN35","Log4NetLevel":"INFO "}
{"@t":"2025-08-29T19:41:42.8202921Z","@mt":"{LogPrefix} Tasks {TaskStatus}, terminated","LogPrefix":"[ScheduledPublishing] ","TaskStatus":"cancelled","SourceContext":"Umbraco.Web.Scheduling.BackgroundTaskRunner","ProcessId":120252,"ProcessName":"w3wp","ThreadId":660,"AppDomainId":2,"AppDomainAppId":"LMW3SVC14ROOT","MachineName":"DESKTOP-3G1QN35","Log4NetLevel":"INFO "}
{"@t":"2025-08-29T19:41:42.8224945Z","@mt":"{LogPrefix} Terminating {Immediate}","LogPrefix":"[Umbraco.Web.Scheduling.IBackgroundTask] ","Immediate":"","SourceContext":"Umbraco.Web.Scheduling.BackgroundTaskRunner","ProcessId":120252,"ProcessName":"w3wp","ThreadId":408,"AppDomainId":2,"AppDomainAppId":"LMW3SVC14ROOT","MachineName":"DESKTOP-3G1QN35","Log4NetLevel":"INFO "}
{"@t":"2025-08-29T19:41:42.8234943Z","@mt":"{LogPrefix} Canceling tasks","LogPrefix":"[Umbraco.Web.Scheduling.IBackgroundTask] ","SourceContext":"Umbraco.Web.Scheduling.BackgroundTaskRunner","ProcessId":120252,"ProcessName":"w3wp","ThreadId":711,"AppDomainId":2,"AppDomainAppId":"LMW3SVC14ROOT","MachineName":"DESKTOP-3G1QN35","Log4NetLevel":"INFO "}
{"@t":"2025-08-29T19:41:42.8234943Z","@mt":"{LogPrefix} Tasks {TaskStatus}, terminated","LogPrefix":"[Umbraco.Web.Scheduling.IBackgroundTask] ","TaskStatus":"cancelled","SourceContext":"Umbraco.Web.Scheduling.BackgroundTaskRunner","ProcessId":120252,"ProcessName":"w3wp","ThreadId":711,"AppDomainId":2,"AppDomainAppId":"LMW3SVC14ROOT","MachineName":"DESKTOP-3G1QN35","Log4NetLevel":"INFO "}
{"@t":"2025-08-29T19:41:44.7649286Z","@mt":"{LogPrefix} Canceling tasks","LogPrefix":"[ServerInstProcess] ","SourceContext":"Umbraco.Web.Scheduling.BackgroundTaskRunner","ProcessId":120252,"ProcessName":"w3wp","ThreadId":717,"AppDomainId":2,"AppDomainAppId":"LMW3SVC14ROOT","MachineName":"DESKTOP-3G1QN35","Log4NetLevel":"INFO "}
{"@t":"2025-08-29T19:41:44.8254390Z","@mt":"{LogPrefix} Canceling tasks","LogPrefix":"[TempFileCleanup] ","SourceContext":"Umbraco.Web.Scheduling.BackgroundTaskRunner","ProcessId":120252,"ProcessName":"w3wp","ThreadId":425,"AppDomainId":2,"AppDomainAppId":"LMW3SVC14ROOT","MachineName":"DESKTOP-3G1QN35","Log4NetLevel":"INFO "}
{"@t":"2025-08-29T19:41:44.8254390Z","@mt":"{LogPrefix} Canceling tasks","LogPrefix":"[ServerRegistration] ","SourceContext":"Umbraco.Web.Scheduling.BackgroundTaskRunner","ProcessId":120252,"ProcessName":"w3wp","ThreadId":203,"AppDomainId":2,"AppDomainAppId":"LMW3SVC14ROOT","MachineName":"DESKTOP-3G1QN35","Log4NetLevel":"INFO "}
{"@t":"2025-08-29T19:41:44.8254390Z","@mt":"{LogPrefix} Canceling tasks","LogPrefix":"[Umbraco.Web.Scheduling.IBackgroundTask] ","SourceContext":"Umbraco.Web.Scheduling.BackgroundTaskRunner","ProcessId":120252,"ProcessName":"w3wp","ThreadId":711,"AppDomainId":2,"AppDomainAppId":"LMW3SVC14ROOT","MachineName":"DESKTOP-3G1QN35","Log4NetLevel":"INFO "}
{"@t":"2025-08-29T19:41:44.8254390Z","@mt":"{LogPrefix} Canceling tasks","LogPrefix":"[RebuildIndexesOnStartup] ","SourceContext":"Umbraco.Web.Scheduling.BackgroundTaskRunner","ProcessId":120252,"ProcessName":"w3wp","ThreadId":400,"AppDomainId":2,"AppDomainAppId":"LMW3SVC14ROOT","MachineName":"DESKTOP-3G1QN35","Log4NetLevel":"INFO "}
{"@t":"2025-08-29T19:41:44.8254390Z","@mt":"{LogPrefix} Canceling tasks","LogPrefix":"[HealthCheckNotifier] ","SourceContext":"Umbraco.Web.Scheduling.BackgroundTaskRunner","ProcessId":120252,"ProcessName":"w3wp","ThreadId":175,"AppDomainId":2,"AppDomainAppId":"LMW3SVC14ROOT","MachineName":"DESKTOP-3G1QN35","Log4NetLevel":"INFO "}
{"@t":"2025-08-29T19:41:44.8254390Z","@mt":"{LogPrefix} Canceling tasks","LogPrefix":"[ContentVersionCleanup] ","SourceContext":"Umbraco.Web.Scheduling.BackgroundTaskRunner","ProcessId":120252,"ProcessName":"w3wp","ThreadId":40,"AppDomainId":2,"AppDomainAppId":"LMW3SVC14ROOT","MachineName":"DESKTOP-3G1QN35","Log4NetLevel":"INFO "}
{"@t":"2025-08-29T19:41:44.8254390Z","@mt":"{LogPrefix} Canceling tasks","LogPrefix":"[LogScrubber] ","SourceContext":"Umbraco.Web.Scheduling.BackgroundTaskRunner","ProcessId":120252,"ProcessName":"w3wp","ThreadId":380,"AppDomainId":2,"AppDomainAppId":"LMW3SVC14ROOT","MachineName":"DESKTOP-3G1QN35","Log4NetLevel":"INFO "}
{"@t":"2025-08-29T19:41:44.8254390Z","@mt":"{LogPrefix} Canceling tasks","LogPrefix":"[TelemetryReporter] ","SourceContext":"Umbraco.Web.Scheduling.BackgroundTaskRunner","ProcessId":120252,"ProcessName":"w3wp","ThreadId":661,"AppDomainId":2,"AppDomainAppId":"LMW3SVC14ROOT","MachineName":"DESKTOP-3G1QN35","Log4NetLevel":"INFO "}
{"@t":"2025-08-29T19:41:44.8254390Z","@mt":"{LogPrefix} Canceling tasks","LogPrefix":"[ScheduledTasks] ","SourceContext":"Umbraco.Web.Scheduling.BackgroundTaskRunner","ProcessId":120252,"ProcessName":"w3wp","ThreadId":132,"AppDomainId":2,"AppDomainAppId":"LMW3SVC14ROOT","MachineName":"DESKTOP-3G1QN35","Log4NetLevel":"INFO "}
{"@t":"2025-08-29T19:41:44.8254390Z","@mt":"{LogPrefix} Canceling tasks","LogPrefix":"[KeepAlive] ","SourceContext":"Umbraco.Web.Scheduling.BackgroundTaskRunner","ProcessId":120252,"ProcessName":"w3wp","ThreadId":187,"AppDomainId":2,"AppDomainAppId":"LMW3SVC14ROOT","MachineName":"DESKTOP-3G1QN35","Log4NetLevel":"INFO "}
{"@t":"2025-08-29T19:41:44.8254390Z","@mt":"{LogPrefix} Canceling tasks","LogPrefix":"[ScheduledPublishing] ","SourceContext":"Umbraco.Web.Scheduling.BackgroundTaskRunner","ProcessId":120252,"ProcessName":"w3wp","ThreadId":435,"AppDomainId":2,"AppDomainAppId":"LMW3SVC14ROOT","MachineName":"DESKTOP-3G1QN35","Log4NetLevel":"INFO "}
{"@t":"2025-08-29T19:42:12.9159238Z","@mt":"Application shutdown. Details: {ShutdownReason}\r\n\r\n_shutDownMessage={ShutdownMessage}\r\n\r\n_shutDownStack={ShutdownStack}","ShutdownReason":"HostingEnvironment","ShutdownMessage":"HostingEnvironment initiated shutdown\r\nHostingEnvironment caused shutdown","ShutdownStack":"   at System.Environment.GetStackTrace(Exception e, Boolean needFileInfo)\r\n   at System.Environment.get_StackTrace()\r\n   at System.Web.Hosting.HostingEnvironment.InitiateShutdownInternal()\r\n   at System.Web.Hosting.HostingEnvironment.InitiateShutdownWithoutDemand()\r\n   at System.Web.Hosting.PipelineRuntime.StopProcessing()","SourceContext":"Umbraco.Web.UmbracoApplicationBase","ProcessId":120252,"ProcessName":"w3wp","ThreadId":203,"AppDomainId":2,"AppDomainAppId":"LMW3SVC14ROOT","MachineName":"DESKTOP-3G1QN35","Log4NetLevel":"INFO "}
