{"@t":"2025-07-25T06:59:56.0506502Z","@mt":"Scheduled health check results:","SourceContext":"Umbraco.Web.HealthCheck.HealthCheckResults","ProcessId":6808,"ProcessName":"w3wp","ThreadId":472,"AppDomainId":3,"AppDomainAppId":"LMW3SVC14ROOT","MachineName":"DESKTOP-3G1QN35","Log4NetLevel":"INFO "}
{"@t":"2025-07-25T06:59:56.0506502Z","@mt":"Checks for '{HealthCheckName}' all completed successfully.","HealthCheckName":"Folder & File Permissions","SourceContext":"Umbraco.Web.HealthCheck.HealthCheckResults","ProcessId":6808,"ProcessName":"w3wp","ThreadId":472,"AppDomainId":3,"AppDomainAppId":"LMW3SVC14ROOT","MachineName":"DESKTOP-3G1QN35","Log4NetLevel":"INFO "}
{"@t":"2025-07-25T06:59:56.0506502Z","@mt":"Result for {HealthCheckName}: {HealthCheckResult}, Message: '{HealthCheckMessage}'","HealthCheckName":"Folder & File Permissions","HealthCheckResult":"Success","HealthCheckMessage":"All folders have the correct permissions set.","SourceContext":"Umbraco.Web.HealthCheck.HealthCheckResults","ProcessId":6808,"ProcessName":"w3wp","ThreadId":472,"AppDomainId":3,"AppDomainAppId":"LMW3SVC14ROOT","MachineName":"DESKTOP-3G1QN35","Log4NetLevel":"INFO "}
{"@t":"2025-07-25T06:59:56.0506502Z","@mt":"Result for {HealthCheckName}: {HealthCheckResult}, Message: '{HealthCheckMessage}'","HealthCheckName":"Folder & File Permissions","HealthCheckResult":"Success","HealthCheckMessage":"All files have the correct permissions set.","SourceContext":"Umbraco.Web.HealthCheck.HealthCheckResults","ProcessId":6808,"ProcessName":"w3wp","ThreadId":472,"AppDomainId":3,"AppDomainAppId":"LMW3SVC14ROOT","MachineName":"DESKTOP-3G1QN35","Log4NetLevel":"INFO "}
{"@t":"2025-07-25T06:59:56.0506502Z","@mt":"Checks for '{HealthCheckName}' completed with errors.","@l":"Warning","HealthCheckName":"SMTP Settings","SourceContext":"Umbraco.Web.HealthCheck.HealthCheckResults","ProcessId":6808,"ProcessName":"w3wp","ThreadId":472,"AppDomainId":3,"AppDomainAppId":"LMW3SVC14ROOT","MachineName":"DESKTOP-3G1QN35","Log4NetLevel":"WARN "}
{"@t":"2025-07-25T06:59:56.0506502Z","@mt":"Result for {HealthCheckName}: {HealthCheckResult}, Message: '{HealthCheckMessage}'","HealthCheckName":"SMTP Settings","HealthCheckResult":"Error","HealthCheckMessage":"In the Web.config file system.net/mailsettings section, the host is not configured.","SourceContext":"Umbraco.Web.HealthCheck.HealthCheckResults","ProcessId":6808,"ProcessName":"w3wp","ThreadId":472,"AppDomainId":3,"AppDomainAppId":"LMW3SVC14ROOT","MachineName":"DESKTOP-3G1QN35","Log4NetLevel":"INFO "}
{"@t":"2025-07-25T06:59:56.0506502Z","@mt":"Checks for '{HealthCheckName}' completed with errors.","@l":"Warning","HealthCheckName":"Application URL Configuration","SourceContext":"Umbraco.Web.HealthCheck.HealthCheckResults","ProcessId":6808,"ProcessName":"w3wp","ThreadId":472,"AppDomainId":3,"AppDomainAppId":"LMW3SVC14ROOT","MachineName":"DESKTOP-3G1QN35","Log4NetLevel":"WARN "}
{"@t":"2025-07-25T06:59:56.0506502Z","@mt":"Result for {HealthCheckName}: {HealthCheckResult}, Message: '{HealthCheckMessage}'","HealthCheckName":"Application URL Configuration","HealthCheckResult":"Warning","HealthCheckMessage":"The 'umbracoApplicationUrl' option is not set in your umbracoSettings.config file.","SourceContext":"Umbraco.Web.HealthCheck.HealthCheckResults","ProcessId":6808,"ProcessName":"w3wp","ThreadId":472,"AppDomainId":3,"AppDomainAppId":"LMW3SVC14ROOT","MachineName":"DESKTOP-3G1QN35","Log4NetLevel":"INFO "}
{"@t":"2025-07-25T06:59:56.0506502Z","@mt":"Checks for '{HealthCheckName}' completed with errors.","@l":"Warning","HealthCheckName":"Cross-site scripting Protection (X-XSS-Protection header)","SourceContext":"Umbraco.Web.HealthCheck.HealthCheckResults","ProcessId":6808,"ProcessName":"w3wp","ThreadId":472,"AppDomainId":3,"AppDomainAppId":"LMW3SVC14ROOT","MachineName":"DESKTOP-3G1QN35","Log4NetLevel":"WARN "}
{"@t":"2025-07-25T06:59:56.0506502Z","@mt":"Result for {HealthCheckName}: {HealthCheckResult}, Message: '{HealthCheckMessage}'","HealthCheckName":"Cross-site scripting Protection (X-XSS-Protection header)","HealthCheckResult":"Error","HealthCheckMessage":"The header <strong>X-XSS-Protection</strong> was not found.","SourceContext":"Umbraco.Web.HealthCheck.HealthCheckResults","ProcessId":6808,"ProcessName":"w3wp","ThreadId":472,"AppDomainId":3,"AppDomainAppId":"LMW3SVC14ROOT","MachineName":"DESKTOP-3G1QN35","Log4NetLevel":"INFO "}
{"@t":"2025-07-25T06:59:56.0506502Z","@mt":"Checks for '{HealthCheckName}' completed with errors.","@l":"Warning","HealthCheckName":"Cookie hijacking and protocol downgrade attacks Protection (Strict-Transport-Security Header (HSTS))","SourceContext":"Umbraco.Web.HealthCheck.HealthCheckResults","ProcessId":6808,"ProcessName":"w3wp","ThreadId":472,"AppDomainId":3,"AppDomainAppId":"LMW3SVC14ROOT","MachineName":"DESKTOP-3G1QN35","Log4NetLevel":"WARN "}
{"@t":"2025-07-25T06:59:56.0506502Z","@mt":"Result for {HealthCheckName}: {HealthCheckResult}, Message: '{HealthCheckMessage}'","HealthCheckName":"Cookie hijacking and protocol downgrade attacks Protection (Strict-Transport-Security Header (HSTS))","HealthCheckResult":"Error","HealthCheckMessage":"The header <strong>Strict-Transport-Security</strong> was not found.","SourceContext":"Umbraco.Web.HealthCheck.HealthCheckResults","ProcessId":6808,"ProcessName":"w3wp","ThreadId":472,"AppDomainId":3,"AppDomainAppId":"LMW3SVC14ROOT","MachineName":"DESKTOP-3G1QN35","Log4NetLevel":"INFO "}
{"@t":"2025-07-25T06:59:56.0506502Z","@mt":"Checks for '{HealthCheckName}' completed with errors.","@l":"Warning","HealthCheckName":"Content/MIME Sniffing Protection","SourceContext":"Umbraco.Web.HealthCheck.HealthCheckResults","ProcessId":6808,"ProcessName":"w3wp","ThreadId":472,"AppDomainId":3,"AppDomainAppId":"LMW3SVC14ROOT","MachineName":"DESKTOP-3G1QN35","Log4NetLevel":"WARN "}
{"@t":"2025-07-25T06:59:56.0506502Z","@mt":"Result for {HealthCheckName}: {HealthCheckResult}, Message: '{HealthCheckMessage}'","HealthCheckName":"Content/MIME Sniffing Protection","HealthCheckResult":"Error","HealthCheckMessage":"The header or meta-tag <strong>X-Content-Type-Options</strong> used to protect against MIME sniffing vulnerabilities was not found.","SourceContext":"Umbraco.Web.HealthCheck.HealthCheckResults","ProcessId":6808,"ProcessName":"w3wp","ThreadId":472,"AppDomainId":3,"AppDomainAppId":"LMW3SVC14ROOT","MachineName":"DESKTOP-3G1QN35","Log4NetLevel":"INFO "}
{"@t":"2025-07-25T06:59:56.0506502Z","@mt":"Checks for '{HealthCheckName}' all completed successfully.","HealthCheckName":"Excessive Headers","SourceContext":"Umbraco.Web.HealthCheck.HealthCheckResults","ProcessId":6808,"ProcessName":"w3wp","ThreadId":472,"AppDomainId":3,"AppDomainAppId":"LMW3SVC14ROOT","MachineName":"DESKTOP-3G1QN35","Log4NetLevel":"INFO "}
{"@t":"2025-07-25T06:59:56.0506502Z","@mt":"Result for {HealthCheckName}: {HealthCheckResult}, Message: '{HealthCheckMessage}'","HealthCheckName":"Excessive Headers","HealthCheckResult":"Success","HealthCheckMessage":"No headers revealing information about the website technology were found.","SourceContext":"Umbraco.Web.HealthCheck.HealthCheckResults","ProcessId":6808,"ProcessName":"w3wp","ThreadId":472,"AppDomainId":3,"AppDomainAppId":"LMW3SVC14ROOT","MachineName":"DESKTOP-3G1QN35","Log4NetLevel":"INFO "}
{"@t":"2025-07-25T06:59:56.0506502Z","@mt":"Checks for '{HealthCheckName}' completed with errors.","@l":"Warning","HealthCheckName":"Click-Jacking Protection","SourceContext":"Umbraco.Web.HealthCheck.HealthCheckResults","ProcessId":6808,"ProcessName":"w3wp","ThreadId":472,"AppDomainId":3,"AppDomainAppId":"LMW3SVC14ROOT","MachineName":"DESKTOP-3G1QN35","Log4NetLevel":"WARN "}
{"@t":"2025-07-25T06:59:56.0506502Z","@mt":"Result for {HealthCheckName}: {HealthCheckResult}, Message: '{HealthCheckMessage}'","HealthCheckName":"Click-Jacking Protection","HealthCheckResult":"Error","HealthCheckMessage":"The header or meta-tag <strong>X-Frame-Options</strong> used to control whether a site can be IFRAMEd by another was not found.","SourceContext":"Umbraco.Web.HealthCheck.HealthCheckResults","ProcessId":6808,"ProcessName":"w3wp","ThreadId":472,"AppDomainId":3,"AppDomainAppId":"LMW3SVC14ROOT","MachineName":"DESKTOP-3G1QN35","Log4NetLevel":"INFO "}
{"@t":"2025-07-25T06:59:56.0506502Z","@mt":"Checks for '{HealthCheckName}' completed with errors.","@l":"Warning","HealthCheckName":"HTTPS Configuration","SourceContext":"Umbraco.Web.HealthCheck.HealthCheckResults","ProcessId":6808,"ProcessName":"w3wp","ThreadId":472,"AppDomainId":3,"AppDomainAppId":"LMW3SVC14ROOT","MachineName":"DESKTOP-3G1QN35","Log4NetLevel":"WARN "}
{"@t":"2025-07-25T06:59:56.0506502Z","@mt":"Result for {HealthCheckName}: {HealthCheckResult}, Message: '{HealthCheckMessage}'","HealthCheckName":"HTTPS Configuration","HealthCheckResult":"Error","HealthCheckMessage":"You are currently not viewing the site using the HTTPS scheme.","SourceContext":"Umbraco.Web.HealthCheck.HealthCheckResults","ProcessId":6808,"ProcessName":"w3wp","ThreadId":472,"AppDomainId":3,"AppDomainAppId":"LMW3SVC14ROOT","MachineName":"DESKTOP-3G1QN35","Log4NetLevel":"INFO "}
{"@t":"2025-07-25T06:59:56.0506502Z","@mt":"Result for {HealthCheckName}: {HealthCheckResult}, Message: '{HealthCheckMessage}'","HealthCheckName":"HTTPS Configuration","HealthCheckResult":"Info","HealthCheckMessage":"The appSetting 'Umbraco.Core.UseHttps' is set to 'false' in your web.config file. Once you access this site using the HTTPS scheme, that should be set to 'true'.","SourceContext":"Umbraco.Web.HealthCheck.HealthCheckResults","ProcessId":6808,"ProcessName":"w3wp","ThreadId":472,"AppDomainId":3,"AppDomainAppId":"LMW3SVC14ROOT","MachineName":"DESKTOP-3G1QN35","Log4NetLevel":"INFO "}
{"@t":"2025-07-25T06:59:56.0506502Z","@mt":"Result for {HealthCheckName}: {HealthCheckResult}, Message: '{HealthCheckMessage}'","HealthCheckName":"HTTPS Configuration","HealthCheckResult":"Error","HealthCheckMessage":"Error pinging the URL https://localhost.tspadel.co.uk/umbraco - 'Unable to connect to the remote server'","SourceContext":"Umbraco.Web.HealthCheck.HealthCheckResults","ProcessId":6808,"ProcessName":"w3wp","ThreadId":472,"AppDomainId":3,"AppDomainAppId":"LMW3SVC14ROOT","MachineName":"DESKTOP-3G1QN35","Log4NetLevel":"INFO "}
{"@t":"2025-07-25T06:59:56.0506502Z","@mt":"Checks for '{HealthCheckName}' all completed successfully.","HealthCheckName":"Database data integrity check","SourceContext":"Umbraco.Web.HealthCheck.HealthCheckResults","ProcessId":6808,"ProcessName":"w3wp","ThreadId":472,"AppDomainId":3,"AppDomainAppId":"LMW3SVC14ROOT","MachineName":"DESKTOP-3G1QN35","Log4NetLevel":"INFO "}
{"@t":"2025-07-25T06:59:56.0506502Z","@mt":"Result for {HealthCheckName}: {HealthCheckResult}, Message: '{HealthCheckMessage}'","HealthCheckName":"Database data integrity check","HealthCheckResult":"Success","HealthCheckMessage":"<p>All document paths are valid</p>\r\n","SourceContext":"Umbraco.Web.HealthCheck.HealthCheckResults","ProcessId":6808,"ProcessName":"w3wp","ThreadId":472,"AppDomainId":3,"AppDomainAppId":"LMW3SVC14ROOT","MachineName":"DESKTOP-3G1QN35","Log4NetLevel":"INFO "}
{"@t":"2025-07-25T06:59:56.0506502Z","@mt":"Result for {HealthCheckName}: {HealthCheckResult}, Message: '{HealthCheckMessage}'","HealthCheckName":"Database data integrity check","HealthCheckResult":"Success","HealthCheckMessage":"<p>All media paths are valid</p>\r\n","SourceContext":"Umbraco.Web.HealthCheck.HealthCheckResults","ProcessId":6808,"ProcessName":"w3wp","ThreadId":472,"AppDomainId":3,"AppDomainAppId":"LMW3SVC14ROOT","MachineName":"DESKTOP-3G1QN35","Log4NetLevel":"INFO "}
{"@t":"2025-07-25T06:59:56.0506502Z","@mt":"Checks for '{HealthCheckName}' completed with errors.","@l":"Warning","HealthCheckName":"Macro errors","SourceContext":"Umbraco.Web.HealthCheck.HealthCheckResults","ProcessId":6808,"ProcessName":"w3wp","ThreadId":472,"AppDomainId":3,"AppDomainAppId":"LMW3SVC14ROOT","MachineName":"DESKTOP-3G1QN35","Log4NetLevel":"WARN "}
{"@t":"2025-07-25T06:59:56.0506502Z","@mt":"Result for {HealthCheckName}: {HealthCheckResult}, Message: '{HealthCheckMessage}'","HealthCheckName":"Macro errors","HealthCheckResult":"Error","HealthCheckMessage":"MacroErrors are set to 'throw' which will prevent some or all pages in your site from loading completely if there are any errors in macros. Rectifying this will set the value to 'inline'.","SourceContext":"Umbraco.Web.HealthCheck.HealthCheckResults","ProcessId":6808,"ProcessName":"w3wp","ThreadId":472,"AppDomainId":3,"AppDomainAppId":"LMW3SVC14ROOT","MachineName":"DESKTOP-3G1QN35","Log4NetLevel":"INFO "}
{"@t":"2025-07-25T06:59:56.0506502Z","@mt":"Checks for '{HealthCheckName}' completed with errors.","@l":"Warning","HealthCheckName":"Notification Email Settings","SourceContext":"Umbraco.Web.HealthCheck.HealthCheckResults","ProcessId":6808,"ProcessName":"w3wp","ThreadId":472,"AppDomainId":3,"AppDomainAppId":"LMW3SVC14ROOT","MachineName":"DESKTOP-3G1QN35","Log4NetLevel":"WARN "}
{"@t":"2025-07-25T06:59:56.0506502Z","@mt":"Result for {HealthCheckName}: {HealthCheckResult}, Message: '{HealthCheckMessage}'","HealthCheckName":"Notification Email Settings","HealthCheckResult":"Error","HealthCheckMessage":"Notification email is still set to the default value of <strong>your@email.here</strong>.","SourceContext":"Umbraco.Web.HealthCheck.HealthCheckResults","ProcessId":6808,"ProcessName":"w3wp","ThreadId":472,"AppDomainId":3,"AppDomainAppId":"LMW3SVC14ROOT","MachineName":"DESKTOP-3G1QN35","Log4NetLevel":"INFO "}
{"@t":"2025-07-25T06:59:56.0506502Z","@mt":"Checks for '{HealthCheckName}' all completed successfully.","HealthCheckName":"Try Skip IIS Custom Errors","SourceContext":"Umbraco.Web.HealthCheck.HealthCheckResults","ProcessId":6808,"ProcessName":"w3wp","ThreadId":472,"AppDomainId":3,"AppDomainAppId":"LMW3SVC14ROOT","MachineName":"DESKTOP-3G1QN35","Log4NetLevel":"INFO "}
{"@t":"2025-07-25T06:59:56.0506502Z","@mt":"Result for {HealthCheckName}: {HealthCheckResult}, Message: '{HealthCheckMessage}'","HealthCheckName":"Try Skip IIS Custom Errors","HealthCheckResult":"Success","HealthCheckMessage":"Try Skip IIS Custom Errors is set to 'true' and you're using IIS version '10.0'.","SourceContext":"Umbraco.Web.HealthCheck.HealthCheckResults","ProcessId":6808,"ProcessName":"w3wp","ThreadId":472,"AppDomainId":3,"AppDomainAppId":"LMW3SVC14ROOT","MachineName":"DESKTOP-3G1QN35","Log4NetLevel":"INFO "}
{"@t":"2025-07-25T06:59:56.0506502Z","@mt":"Checks for '{HealthCheckName}' all completed successfully.","HealthCheckName":"Custom Errors","SourceContext":"Umbraco.Web.HealthCheck.HealthCheckResults","ProcessId":6808,"ProcessName":"w3wp","ThreadId":472,"AppDomainId":3,"AppDomainAppId":"LMW3SVC14ROOT","MachineName":"DESKTOP-3G1QN35","Log4NetLevel":"INFO "}
{"@t":"2025-07-25T06:59:56.0506502Z","@mt":"Result for {HealthCheckName}: {HealthCheckResult}, Message: '{HealthCheckMessage}'","HealthCheckName":"Custom Errors","HealthCheckResult":"Success","HealthCheckMessage":"Custom errors are set to 'RemoteOnly'.","SourceContext":"Umbraco.Web.HealthCheck.HealthCheckResults","ProcessId":6808,"ProcessName":"w3wp","ThreadId":472,"AppDomainId":3,"AppDomainAppId":"LMW3SVC14ROOT","MachineName":"DESKTOP-3G1QN35","Log4NetLevel":"INFO "}
{"@t":"2025-07-25T06:59:56.0506502Z","@mt":"Checks for '{HealthCheckName}' all completed successfully.","HealthCheckName":"Trace Mode","SourceContext":"Umbraco.Web.HealthCheck.HealthCheckResults","ProcessId":6808,"ProcessName":"w3wp","ThreadId":472,"AppDomainId":3,"AppDomainAppId":"LMW3SVC14ROOT","MachineName":"DESKTOP-3G1QN35","Log4NetLevel":"INFO "}
{"@t":"2025-07-25T06:59:56.0506502Z","@mt":"Result for {HealthCheckName}: {HealthCheckResult}, Message: '{HealthCheckMessage}'","HealthCheckName":"Trace Mode","HealthCheckResult":"Success","HealthCheckMessage":"Trace mode is disabled.","SourceContext":"Umbraco.Web.HealthCheck.HealthCheckResults","ProcessId":6808,"ProcessName":"w3wp","ThreadId":472,"AppDomainId":3,"AppDomainAppId":"LMW3SVC14ROOT","MachineName":"DESKTOP-3G1QN35","Log4NetLevel":"INFO "}
{"@t":"2025-07-25T06:59:56.0506502Z","@mt":"Checks for '{HealthCheckName}' completed with errors.","@l":"Warning","HealthCheckName":"Debug Compilation Mode","SourceContext":"Umbraco.Web.HealthCheck.HealthCheckResults","ProcessId":6808,"ProcessName":"w3wp","ThreadId":472,"AppDomainId":3,"AppDomainAppId":"LMW3SVC14ROOT","MachineName":"DESKTOP-3G1QN35","Log4NetLevel":"WARN "}
{"@t":"2025-07-25T06:59:56.0506502Z","@mt":"Result for {HealthCheckName}: {HealthCheckResult}, Message: '{HealthCheckMessage}'","HealthCheckName":"Debug Compilation Mode","HealthCheckResult":"Error","HealthCheckMessage":"Debug compilation mode is currently enabled. It is recommended to disable this setting before go live.","SourceContext":"Umbraco.Web.HealthCheck.HealthCheckResults","ProcessId":6808,"ProcessName":"w3wp","ThreadId":472,"AppDomainId":3,"AppDomainAppId":"LMW3SVC14ROOT","MachineName":"DESKTOP-3G1QN35","Log4NetLevel":"INFO "}
{"@t":"2025-07-25T11:56:17.5800680Z","@mt":"{LogPrefix} Terminating {Immediate}","LogPrefix":"[TelemetryReporter] ","Immediate":"","SourceContext":"Umbraco.Web.Scheduling.BackgroundTaskRunner","ProcessId":6808,"ProcessName":"w3wp","ThreadId":428,"AppDomainId":3,"AppDomainAppId":"LMW3SVC14ROOT","MachineName":"DESKTOP-3G1QN35","Log4NetLevel":"INFO "}
{"@t":"2025-07-25T11:56:17.5800680Z","@mt":"{LogPrefix} Terminating {Immediate}","LogPrefix":"[ContentVersionCleanup] ","Immediate":"","SourceContext":"Umbraco.Web.Scheduling.BackgroundTaskRunner","ProcessId":6808,"ProcessName":"w3wp","ThreadId":428,"AppDomainId":3,"AppDomainAppId":"LMW3SVC14ROOT","MachineName":"DESKTOP-3G1QN35","Log4NetLevel":"INFO "}
{"@t":"2025-07-25T11:56:17.5815754Z","@mt":"Stopping ({SignalSource})","SignalSource":"environment","SourceContext":"Umbraco.Core.Runtime.MainDom","ProcessId":6808,"ProcessName":"w3wp","ThreadId":428,"AppDomainId":3,"AppDomainAppId":"LMW3SVC14ROOT","MachineName":"DESKTOP-3G1QN35","Log4NetLevel":"INFO "}
{"@t":"2025-07-25T11:56:17.5845801Z","@mt":"{StartMessage} [Timing {TimingId}]","StartMessage":"Examine shutting down","TimingId":"a83ec6b","SourceContext":"Umbraco.Web.Search.ExamineComponent","ProcessId":6808,"ProcessName":"w3wp","ThreadId":428,"AppDomainId":3,"AppDomainAppId":"LMW3SVC14ROOT","MachineName":"DESKTOP-3G1QN35","Log4NetLevel":"INFO "}
{"@t":"2025-07-25T11:56:17.5855825Z","@mt":"{LogPrefix} Canceling tasks","LogPrefix":"[ContentVersionCleanup] ","SourceContext":"Umbraco.Web.Scheduling.BackgroundTaskRunner","ProcessId":6808,"ProcessName":"w3wp","ThreadId":195,"AppDomainId":3,"AppDomainAppId":"LMW3SVC14ROOT","MachineName":"DESKTOP-3G1QN35","Log4NetLevel":"INFO "}
{"@t":"2025-07-25T11:56:17.5855825Z","@mt":"{LogPrefix} Canceling tasks","LogPrefix":"[TelemetryReporter] ","SourceContext":"Umbraco.Web.Scheduling.BackgroundTaskRunner","ProcessId":6808,"ProcessName":"w3wp","ThreadId":58,"AppDomainId":3,"AppDomainAppId":"LMW3SVC14ROOT","MachineName":"DESKTOP-3G1QN35","Log4NetLevel":"INFO "}
{"@t":"2025-07-25T11:56:17.5855825Z","@mt":"{LogPrefix} Tasks {TaskStatus}, terminated","LogPrefix":"[ContentVersionCleanup] ","TaskStatus":"cancelled","SourceContext":"Umbraco.Web.Scheduling.BackgroundTaskRunner","ProcessId":6808,"ProcessName":"w3wp","ThreadId":195,"AppDomainId":3,"AppDomainAppId":"LMW3SVC14ROOT","MachineName":"DESKTOP-3G1QN35","Log4NetLevel":"INFO "}
{"@t":"2025-07-25T11:56:17.5855825Z","@mt":"{LogPrefix} Tasks {TaskStatus}, terminated","LogPrefix":"[TelemetryReporter] ","TaskStatus":"cancelled","SourceContext":"Umbraco.Web.Scheduling.BackgroundTaskRunner","ProcessId":6808,"ProcessName":"w3wp","ThreadId":58,"AppDomainId":3,"AppDomainAppId":"LMW3SVC14ROOT","MachineName":"DESKTOP-3G1QN35","Log4NetLevel":"INFO "}
{"@t":"2025-07-25T11:56:17.5930854Z","@mt":"{EndMessage} ({Duration}ms) [Timing {TimingId}]","EndMessage":"Completed.","Duration":8,"TimingId":"a83ec6b","SourceContext":"Umbraco.Web.Search.ExamineComponent","ProcessId":6808,"ProcessName":"w3wp","ThreadId":428,"AppDomainId":3,"AppDomainAppId":"LMW3SVC14ROOT","MachineName":"DESKTOP-3G1QN35","Log4NetLevel":"INFO "}
{"@t":"2025-07-25T11:56:17.6127368Z","@mt":"Released from MainDom","SourceContext":"Umbraco.Web.PublishedCache.NuCache.PublishedSnapshotService","ProcessId":6808,"ProcessName":"w3wp","ThreadId":428,"AppDomainId":3,"AppDomainAppId":"LMW3SVC14ROOT","MachineName":"DESKTOP-3G1QN35","Log4NetLevel":"INFO "}
{"@t":"2025-07-25T11:56:17.6137400Z","@mt":"Released ({SignalSource})","SignalSource":"environment","SourceContext":"Umbraco.Core.Runtime.MainDom","ProcessId":6808,"ProcessName":"w3wp","ThreadId":428,"AppDomainId":3,"AppDomainAppId":"LMW3SVC14ROOT","MachineName":"DESKTOP-3G1QN35","Log4NetLevel":"INFO "}
{"@t":"2025-07-25T11:56:17.6137400Z","@mt":"{LogPrefix} Terminating {Immediate}","LogPrefix":"[Umbraco.Web.Scheduling.IBackgroundTask] ","Immediate":"","SourceContext":"Umbraco.Web.Scheduling.BackgroundTaskRunner","ProcessId":6808,"ProcessName":"w3wp","ThreadId":428,"AppDomainId":3,"AppDomainAppId":"LMW3SVC14ROOT","MachineName":"DESKTOP-3G1QN35","Log4NetLevel":"INFO "}
{"@t":"2025-07-25T11:56:17.6137400Z","@mt":"{LogPrefix} Terminating {Immediate}","LogPrefix":"[KeepAlive] ","Immediate":"","SourceContext":"Umbraco.Web.Scheduling.BackgroundTaskRunner","ProcessId":6808,"ProcessName":"w3wp","ThreadId":428,"AppDomainId":3,"AppDomainAppId":"LMW3SVC14ROOT","MachineName":"DESKTOP-3G1QN35","Log4NetLevel":"INFO "}
{"@t":"2025-07-25T11:56:17.6137400Z","@mt":"{LogPrefix} Terminating {Immediate}","LogPrefix":"[TempFileCleanup] ","Immediate":"","SourceContext":"Umbraco.Web.Scheduling.BackgroundTaskRunner","ProcessId":6808,"ProcessName":"w3wp","ThreadId":428,"AppDomainId":3,"AppDomainAppId":"LMW3SVC14ROOT","MachineName":"DESKTOP-3G1QN35","Log4NetLevel":"INFO "}
{"@t":"2025-07-25T11:56:17.6137400Z","@mt":"{LogPrefix} Canceling tasks","LogPrefix":"[Umbraco.Web.Scheduling.IBackgroundTask] ","SourceContext":"Umbraco.Web.Scheduling.BackgroundTaskRunner","ProcessId":6808,"ProcessName":"w3wp","ThreadId":238,"AppDomainId":3,"AppDomainAppId":"LMW3SVC14ROOT","MachineName":"DESKTOP-3G1QN35","Log4NetLevel":"INFO "}
{"@t":"2025-07-25T11:56:17.6137400Z","@mt":"{LogPrefix} Tasks {TaskStatus}, terminated","LogPrefix":"[Umbraco.Web.Scheduling.IBackgroundTask] ","TaskStatus":"cancelled","SourceContext":"Umbraco.Web.Scheduling.BackgroundTaskRunner","ProcessId":6808,"ProcessName":"w3wp","ThreadId":238,"AppDomainId":3,"AppDomainAppId":"LMW3SVC14ROOT","MachineName":"DESKTOP-3G1QN35","Log4NetLevel":"INFO "}
{"@t":"2025-07-25T11:56:17.6137400Z","@mt":"{LogPrefix} Terminating {Immediate}","LogPrefix":"[ScheduledPublishing] ","Immediate":"","SourceContext":"Umbraco.Web.Scheduling.BackgroundTaskRunner","ProcessId":6808,"ProcessName":"w3wp","ThreadId":428,"AppDomainId":3,"AppDomainAppId":"LMW3SVC14ROOT","MachineName":"DESKTOP-3G1QN35","Log4NetLevel":"INFO "}
{"@t":"2025-07-25T11:56:17.6137400Z","@mt":"{LogPrefix} Canceling tasks","LogPrefix":"[KeepAlive] ","SourceContext":"Umbraco.Web.Scheduling.BackgroundTaskRunner","ProcessId":6808,"ProcessName":"w3wp","ThreadId":418,"AppDomainId":3,"AppDomainAppId":"LMW3SVC14ROOT","MachineName":"DESKTOP-3G1QN35","Log4NetLevel":"INFO "}
{"@t":"2025-07-25T11:56:17.6137400Z","@mt":"{LogPrefix} Terminating {Immediate}","LogPrefix":"[LogScrubber] ","Immediate":"","SourceContext":"Umbraco.Web.Scheduling.BackgroundTaskRunner","ProcessId":6808,"ProcessName":"w3wp","ThreadId":428,"AppDomainId":3,"AppDomainAppId":"LMW3SVC14ROOT","MachineName":"DESKTOP-3G1QN35","Log4NetLevel":"INFO "}
{"@t":"2025-07-25T11:56:17.6137400Z","@mt":"{LogPrefix} Canceling tasks","LogPrefix":"[TempFileCleanup] ","SourceContext":"Umbraco.Web.Scheduling.BackgroundTaskRunner","ProcessId":6808,"ProcessName":"w3wp","ThreadId":55,"AppDomainId":3,"AppDomainAppId":"LMW3SVC14ROOT","MachineName":"DESKTOP-3G1QN35","Log4NetLevel":"INFO "}
{"@t":"2025-07-25T11:56:17.6137400Z","@mt":"{LogPrefix} Tasks {TaskStatus}, terminated","LogPrefix":"[KeepAlive] ","TaskStatus":"cancelled","SourceContext":"Umbraco.Web.Scheduling.BackgroundTaskRunner","ProcessId":6808,"ProcessName":"w3wp","ThreadId":418,"AppDomainId":3,"AppDomainAppId":"LMW3SVC14ROOT","MachineName":"DESKTOP-3G1QN35","Log4NetLevel":"INFO "}
{"@t":"2025-07-25T11:56:17.6137400Z","@mt":"{LogPrefix} Canceling tasks","LogPrefix":"[LogScrubber] ","SourceContext":"Umbraco.Web.Scheduling.BackgroundTaskRunner","ProcessId":6808,"ProcessName":"w3wp","ThreadId":392,"AppDomainId":3,"AppDomainAppId":"LMW3SVC14ROOT","MachineName":"DESKTOP-3G1QN35","Log4NetLevel":"INFO "}
{"@t":"2025-07-25T11:56:17.6137400Z","@mt":"{LogPrefix} Canceling tasks","LogPrefix":"[ScheduledPublishing] ","SourceContext":"Umbraco.Web.Scheduling.BackgroundTaskRunner","ProcessId":6808,"ProcessName":"w3wp","ThreadId":383,"AppDomainId":3,"AppDomainAppId":"LMW3SVC14ROOT","MachineName":"DESKTOP-3G1QN35","Log4NetLevel":"INFO "}
{"@t":"2025-07-25T11:56:17.6137400Z","@mt":"{LogPrefix} Tasks {TaskStatus}, terminated","LogPrefix":"[ScheduledPublishing] ","TaskStatus":"cancelled","SourceContext":"Umbraco.Web.Scheduling.BackgroundTaskRunner","ProcessId":6808,"ProcessName":"w3wp","ThreadId":383,"AppDomainId":3,"AppDomainAppId":"LMW3SVC14ROOT","MachineName":"DESKTOP-3G1QN35","Log4NetLevel":"INFO "}
{"@t":"2025-07-25T11:56:17.6137400Z","@mt":"{LogPrefix} Tasks {TaskStatus}, terminated","LogPrefix":"[TempFileCleanup] ","TaskStatus":"cancelled","SourceContext":"Umbraco.Web.Scheduling.BackgroundTaskRunner","ProcessId":6808,"ProcessName":"w3wp","ThreadId":55,"AppDomainId":3,"AppDomainAppId":"LMW3SVC14ROOT","MachineName":"DESKTOP-3G1QN35","Log4NetLevel":"INFO "}
{"@t":"2025-07-25T11:56:17.6137400Z","@mt":"{LogPrefix} Tasks {TaskStatus}, terminated","LogPrefix":"[LogScrubber] ","TaskStatus":"cancelled","SourceContext":"Umbraco.Web.Scheduling.BackgroundTaskRunner","ProcessId":6808,"ProcessName":"w3wp","ThreadId":392,"AppDomainId":3,"AppDomainAppId":"LMW3SVC14ROOT","MachineName":"DESKTOP-3G1QN35","Log4NetLevel":"INFO "}
{"@t":"2025-07-25T11:56:17.6137400Z","@mt":"{LogPrefix} Terminating {Immediate}","LogPrefix":"[ServerInstProcess] ","Immediate":"","SourceContext":"Umbraco.Web.Scheduling.BackgroundTaskRunner","ProcessId":6808,"ProcessName":"w3wp","ThreadId":428,"AppDomainId":3,"AppDomainAppId":"LMW3SVC14ROOT","MachineName":"DESKTOP-3G1QN35","Log4NetLevel":"INFO "}
{"@t":"2025-07-25T11:56:17.6137400Z","@mt":"{LogPrefix} Terminating {Immediate}","LogPrefix":"[ScheduledTasks] ","Immediate":"","SourceContext":"Umbraco.Web.Scheduling.BackgroundTaskRunner","ProcessId":6808,"ProcessName":"w3wp","ThreadId":428,"AppDomainId":3,"AppDomainAppId":"LMW3SVC14ROOT","MachineName":"DESKTOP-3G1QN35","Log4NetLevel":"INFO "}
{"@t":"2025-07-25T11:56:17.6137400Z","@mt":"{LogPrefix} Terminating {Immediate}","LogPrefix":"[HealthCheckNotifier] ","Immediate":"","SourceContext":"Umbraco.Web.Scheduling.BackgroundTaskRunner","ProcessId":6808,"ProcessName":"w3wp","ThreadId":428,"AppDomainId":3,"AppDomainAppId":"LMW3SVC14ROOT","MachineName":"DESKTOP-3G1QN35","Log4NetLevel":"INFO "}
{"@t":"2025-07-25T11:56:17.6137400Z","@mt":"{LogPrefix} Terminating {Immediate}","LogPrefix":"[RebuildIndexesOnStartup] ","Immediate":"","SourceContext":"Umbraco.Web.Scheduling.BackgroundTaskRunner","ProcessId":6808,"ProcessName":"w3wp","ThreadId":428,"AppDomainId":3,"AppDomainAppId":"LMW3SVC14ROOT","MachineName":"DESKTOP-3G1QN35","Log4NetLevel":"INFO "}
{"@t":"2025-07-25T11:56:17.6137400Z","@mt":"{LogPrefix} Canceling tasks","LogPrefix":"[ScheduledTasks] ","SourceContext":"Umbraco.Web.Scheduling.BackgroundTaskRunner","ProcessId":6808,"ProcessName":"w3wp","ThreadId":5,"AppDomainId":3,"AppDomainAppId":"LMW3SVC14ROOT","MachineName":"DESKTOP-3G1QN35","Log4NetLevel":"INFO "}
{"@t":"2025-07-25T11:56:17.6137400Z","@mt":"{LogPrefix} Tasks {TaskStatus}, terminated","LogPrefix":"[ScheduledTasks] ","TaskStatus":"cancelled","SourceContext":"Umbraco.Web.Scheduling.BackgroundTaskRunner","ProcessId":6808,"ProcessName":"w3wp","ThreadId":5,"AppDomainId":3,"AppDomainAppId":"LMW3SVC14ROOT","MachineName":"DESKTOP-3G1QN35","Log4NetLevel":"INFO "}
{"@t":"2025-07-25T11:56:17.6137400Z","@mt":"{LogPrefix} Canceling tasks","LogPrefix":"[RebuildIndexesOnStartup] ","SourceContext":"Umbraco.Web.Scheduling.BackgroundTaskRunner","ProcessId":6808,"ProcessName":"w3wp","ThreadId":110,"AppDomainId":3,"AppDomainAppId":"LMW3SVC14ROOT","MachineName":"DESKTOP-3G1QN35","Log4NetLevel":"INFO "}
{"@t":"2025-07-25T11:56:17.6137400Z","@mt":"{LogPrefix} Canceling tasks","LogPrefix":"[ServerInstProcess] ","SourceContext":"Umbraco.Web.Scheduling.BackgroundTaskRunner","ProcessId":6808,"ProcessName":"w3wp","ThreadId":109,"AppDomainId":3,"AppDomainAppId":"LMW3SVC14ROOT","MachineName":"DESKTOP-3G1QN35","Log4NetLevel":"INFO "}
{"@t":"2025-07-25T11:56:17.6137400Z","@mt":"{LogPrefix} Tasks {TaskStatus}, terminated","LogPrefix":"[RebuildIndexesOnStartup] ","TaskStatus":"cancelled","SourceContext":"Umbraco.Web.Scheduling.BackgroundTaskRunner","ProcessId":6808,"ProcessName":"w3wp","ThreadId":110,"AppDomainId":3,"AppDomainAppId":"LMW3SVC14ROOT","MachineName":"DESKTOP-3G1QN35","Log4NetLevel":"INFO "}
{"@t":"2025-07-25T11:56:17.6137400Z","@mt":"{LogPrefix} Tasks {TaskStatus}, terminated","LogPrefix":"[ServerInstProcess] ","TaskStatus":"cancelled","SourceContext":"Umbraco.Web.Scheduling.BackgroundTaskRunner","ProcessId":6808,"ProcessName":"w3wp","ThreadId":109,"AppDomainId":3,"AppDomainAppId":"LMW3SVC14ROOT","MachineName":"DESKTOP-3G1QN35","Log4NetLevel":"INFO "}
{"@t":"2025-07-25T11:56:17.6137400Z","@mt":"{LogPrefix} Canceling tasks","LogPrefix":"[HealthCheckNotifier] ","SourceContext":"Umbraco.Web.Scheduling.BackgroundTaskRunner","ProcessId":6808,"ProcessName":"w3wp","ThreadId":426,"AppDomainId":3,"AppDomainAppId":"LMW3SVC14ROOT","MachineName":"DESKTOP-3G1QN35","Log4NetLevel":"INFO "}
{"@t":"2025-07-25T11:56:17.6137400Z","@mt":"{LogPrefix} Tasks {TaskStatus}, terminated","LogPrefix":"[HealthCheckNotifier] ","TaskStatus":"cancelled","SourceContext":"Umbraco.Web.Scheduling.BackgroundTaskRunner","ProcessId":6808,"ProcessName":"w3wp","ThreadId":426,"AppDomainId":3,"AppDomainAppId":"LMW3SVC14ROOT","MachineName":"DESKTOP-3G1QN35","Log4NetLevel":"INFO "}
{"@t":"2025-07-25T11:56:17.6137400Z","@mt":"{LogPrefix} Terminating {Immediate}","LogPrefix":"[ServerRegistration] ","Immediate":"","SourceContext":"Umbraco.Web.Scheduling.BackgroundTaskRunner","ProcessId":6808,"ProcessName":"w3wp","ThreadId":428,"AppDomainId":3,"AppDomainAppId":"LMW3SVC14ROOT","MachineName":"DESKTOP-3G1QN35","Log4NetLevel":"INFO "}
{"@t":"2025-07-25T11:56:17.6137400Z","@mt":"{LogPrefix} Canceling tasks","LogPrefix":"[ServerRegistration] ","SourceContext":"Umbraco.Web.Scheduling.BackgroundTaskRunner","ProcessId":6808,"ProcessName":"w3wp","ThreadId":187,"AppDomainId":3,"AppDomainAppId":"LMW3SVC14ROOT","MachineName":"DESKTOP-3G1QN35","Log4NetLevel":"INFO "}
{"@t":"2025-07-25T11:56:17.6137400Z","@mt":"{LogPrefix} Tasks {TaskStatus}, terminated","LogPrefix":"[ServerRegistration] ","TaskStatus":"cancelled","SourceContext":"Umbraco.Web.Scheduling.BackgroundTaskRunner","ProcessId":6808,"ProcessName":"w3wp","ThreadId":187,"AppDomainId":3,"AppDomainAppId":"LMW3SVC14ROOT","MachineName":"DESKTOP-3G1QN35","Log4NetLevel":"INFO "}
{"@t":"2025-07-25T11:56:19.5861239Z","@mt":"{LogPrefix} Canceling tasks","LogPrefix":"[TelemetryReporter] ","SourceContext":"Umbraco.Web.Scheduling.BackgroundTaskRunner","ProcessId":6808,"ProcessName":"w3wp","ThreadId":68,"AppDomainId":3,"AppDomainAppId":"LMW3SVC14ROOT","MachineName":"DESKTOP-3G1QN35","Log4NetLevel":"INFO "}
{"@t":"2025-07-25T11:56:19.5861239Z","@mt":"{LogPrefix} Canceling tasks","LogPrefix":"[ContentVersionCleanup] ","SourceContext":"Umbraco.Web.Scheduling.BackgroundTaskRunner","ProcessId":6808,"ProcessName":"w3wp","ThreadId":141,"AppDomainId":3,"AppDomainAppId":"LMW3SVC14ROOT","MachineName":"DESKTOP-3G1QN35","Log4NetLevel":"INFO "}
{"@t":"2025-07-25T11:56:19.6170431Z","@mt":"{LogPrefix} Canceling tasks","LogPrefix":"[RebuildIndexesOnStartup] ","SourceContext":"Umbraco.Web.Scheduling.BackgroundTaskRunner","ProcessId":6808,"ProcessName":"w3wp","ThreadId":110,"AppDomainId":3,"AppDomainAppId":"LMW3SVC14ROOT","MachineName":"DESKTOP-3G1QN35","Log4NetLevel":"INFO "}
{"@t":"2025-07-25T11:56:19.6170431Z","@mt":"{LogPrefix} Canceling tasks","LogPrefix":"[ScheduledTasks] ","SourceContext":"Umbraco.Web.Scheduling.BackgroundTaskRunner","ProcessId":6808,"ProcessName":"w3wp","ThreadId":5,"AppDomainId":3,"AppDomainAppId":"LMW3SVC14ROOT","MachineName":"DESKTOP-3G1QN35","Log4NetLevel":"INFO "}
{"@t":"2025-07-25T11:56:19.6170431Z","@mt":"{LogPrefix} Canceling tasks","LogPrefix":"[ServerInstProcess] ","SourceContext":"Umbraco.Web.Scheduling.BackgroundTaskRunner","ProcessId":6808,"ProcessName":"w3wp","ThreadId":518,"AppDomainId":3,"AppDomainAppId":"LMW3SVC14ROOT","MachineName":"DESKTOP-3G1QN35","Log4NetLevel":"INFO "}
{"@t":"2025-07-25T11:56:19.6170431Z","@mt":"{LogPrefix} Canceling tasks","LogPrefix":"[LogScrubber] ","SourceContext":"Umbraco.Web.Scheduling.BackgroundTaskRunner","ProcessId":6808,"ProcessName":"w3wp","ThreadId":25,"AppDomainId":3,"AppDomainAppId":"LMW3SVC14ROOT","MachineName":"DESKTOP-3G1QN35","Log4NetLevel":"INFO "}
{"@t":"2025-07-25T11:56:19.6170431Z","@mt":"{LogPrefix} Canceling tasks","LogPrefix":"[TempFileCleanup] ","SourceContext":"Umbraco.Web.Scheduling.BackgroundTaskRunner","ProcessId":6808,"ProcessName":"w3wp","ThreadId":137,"AppDomainId":3,"AppDomainAppId":"LMW3SVC14ROOT","MachineName":"DESKTOP-3G1QN35","Log4NetLevel":"INFO "}
{"@t":"2025-07-25T11:56:19.6170431Z","@mt":"{LogPrefix} Canceling tasks","LogPrefix":"[ServerRegistration] ","SourceContext":"Umbraco.Web.Scheduling.BackgroundTaskRunner","ProcessId":6808,"ProcessName":"w3wp","ThreadId":582,"AppDomainId":3,"AppDomainAppId":"LMW3SVC14ROOT","MachineName":"DESKTOP-3G1QN35","Log4NetLevel":"INFO "}
{"@t":"2025-07-25T11:56:19.6170431Z","@mt":"{LogPrefix} Canceling tasks","LogPrefix":"[KeepAlive] ","SourceContext":"Umbraco.Web.Scheduling.BackgroundTaskRunner","ProcessId":6808,"ProcessName":"w3wp","ThreadId":103,"AppDomainId":3,"AppDomainAppId":"LMW3SVC14ROOT","MachineName":"DESKTOP-3G1QN35","Log4NetLevel":"INFO "}
{"@t":"2025-07-25T11:56:19.6170431Z","@mt":"{LogPrefix} Canceling tasks","LogPrefix":"[HealthCheckNotifier] ","SourceContext":"Umbraco.Web.Scheduling.BackgroundTaskRunner","ProcessId":6808,"ProcessName":"w3wp","ThreadId":545,"AppDomainId":3,"AppDomainAppId":"LMW3SVC14ROOT","MachineName":"DESKTOP-3G1QN35","Log4NetLevel":"INFO "}
{"@t":"2025-07-25T11:56:19.6170431Z","@mt":"{LogPrefix} Canceling tasks","LogPrefix":"[ScheduledPublishing] ","SourceContext":"Umbraco.Web.Scheduling.BackgroundTaskRunner","ProcessId":6808,"ProcessName":"w3wp","ThreadId":96,"AppDomainId":3,"AppDomainAppId":"LMW3SVC14ROOT","MachineName":"DESKTOP-3G1QN35","Log4NetLevel":"INFO "}
{"@t":"2025-07-25T11:56:19.6170431Z","@mt":"{LogPrefix} Canceling tasks","LogPrefix":"[Umbraco.Web.Scheduling.IBackgroundTask] ","SourceContext":"Umbraco.Web.Scheduling.BackgroundTaskRunner","ProcessId":6808,"ProcessName":"w3wp","ThreadId":238,"AppDomainId":3,"AppDomainAppId":"LMW3SVC14ROOT","MachineName":"DESKTOP-3G1QN35","Log4NetLevel":"INFO "}
{"@t":"2025-07-25T11:56:47.6772542Z","@mt":"Application shutdown. Details: {ShutdownReason}\r\n\r\n_shutDownMessage={ShutdownMessage}\r\n\r\n_shutDownStack={ShutdownStack}","ShutdownReason":"HostingEnvironment","ShutdownMessage":"HostingEnvironment initiated shutdown\r\nHostingEnvironment caused shutdown","ShutdownStack":"   at System.Environment.GetStackTrace(Exception e, Boolean needFileInfo)\r\n   at System.Environment.get_StackTrace()\r\n   at System.Web.Hosting.HostingEnvironment.InitiateShutdownInternal()\r\n   at System.Web.Hosting.HostingEnvironment.InitiateShutdownWithoutDemand()\r\n   at System.Web.Hosting.PipelineRuntime.StopProcessing()","SourceContext":"Umbraco.Web.UmbracoApplicationBase","ProcessId":6808,"ProcessName":"w3wp","ThreadId":187,"AppDomainId":3,"AppDomainAppId":"LMW3SVC14ROOT","MachineName":"DESKTOP-3G1QN35","Log4NetLevel":"INFO "}
